{
    "wodu": [
        {"text": "السِّواك . \n\nوذلك قبل البدء بالوضوء ، أو قبل المضمضة ، وهذا هو الموضع الثاني الذي يُسَنُّ فيه السِّواك - وتقدَّم الموضع الأول - فيُسَنّ لمن أراد الوضوء أن يستاك؛ لحديث أبي هريرة - رضي الله عنه - أنَّ رسول الله - صلَّى الله عليه وسلَّم - قال :  لَوْلَا أَنْ أَشُقَّ عَلَى أُمَّتِي لَأَمَرْتُهُمْ بِالسِّوَاكِ مَعَ كُلِّ وُضُوءٍ  . رواه أحمد برقم (9928) ، رواه ابن خزيمة وصححه (1/73/140) ، والحاكم (1/245) ،والبخاري تعليقًا بصيغة الجزم في باب : سواك الرطب واليابس للصائم. ولحديث عائشة – رضي الله عنها – قالت:  كُنَّا نُعِدُّ لَهُ سِوَاكَهُ وَطَهُورَهُ ، فيَبْعَثُهُ الله مَا شَاءَ أَنْ يَبْعَثَهُ مِنَ اللَّيْلِ ، فَيَتَسَوَّكُ وَيَتَوَضَّأُ وَيُصَلِّي ... رواه مسلم برقم (746). "},
        {"text": "التسمية . \n\n لحديث أبي هريرة - رضي الله عنه - مرفوعاً :  لَا وُضُوءَ لِمَنْ لَمْ يَذْكُرِ اسْمَ الله . رواه أحمد برقم (11371) ، وأبو داود برقم (101)، وابن ماجه برقم (397)."},
        {"text": "غسل الكفين ثلاثًا. \n\n لحديث عثمان - رضي الله عنه - في صِفة وضوء النَّبي - صلَّى الله عليه وسلَّم -  وفيه: دَعَا بِوَضُوءٍ ، فَتَوَضَّأَ فَغَسَلَ كَفَّيْهِ ثَلاَثَ مَرَّاتٍ... ،  ثم قال :  رَأَيْتُ النَّبِيَّ - صَلَّى اللَّهُ عَلَيْهِ وَسَلَّمَ - يَتَوَضَّأُ نَحْوَ وُضُوئِي هَذَا . رواه البخاري برقم (164) ، رواه مسلم برقم (226)"},
        {"text": "التَّيامن في غسل اليدين، والقدمين . \n\n لحديث عائشةَ - رضي الله عنها - قالت :  كَانَ النَّبِيُّ - صَلَّى اللَّهُ عَلَيْهِ وَسَلَّمَ - يُعْجِبُهُ التَّيَمُّنُ فِي تَنَعُّلِهِ وَتَرَجُّلِهِ وَطُهُورِهِ وَفِي شَأْنِهِ كُلِّهِ  . رواه البخاري برقم (168) ، رواه مسلم برقم (268) ."},
        {"text": "البداءة بالمضمضة، والاستنشاق . \n\n لحديث عثمان - رضي الله عنه - في صِفة وضوء النَّبي - صلَّى الله عليه وسلَّم - : ... فَمَضْمَضَ ، وَاسْتَنْثَرَ ، ثُمَّ غَسَلَ وَجْهَهُ ثَلاَثَ مَرَّاتٍ... رواه البخاري برقم (199) ، رواه مسلم برقم (226) ، فإن أخَّر المضمضة والاستنشاق بعد غسل الوجه جاز ."},
        {"text": "المبالغة في المضمضة، والاستنشاق لغير الصائم . \n\n لحديث لقيط بن صبرة - رضي الله عنه - أنَّ النَّبيّ - صلَّى الله عليه وسلَّم - قال له :  أَسْبِغ الوُضُوءَ، وخَلِّلْ بَيْنَ الأصَابِعِ ، وبَالِغْ فِي الاسْتِنْشَاقِ إِلاَّ أَنْ تَكُونَ صَائِماً رواه أحمد برقم (17846) ، وأبو داود برقم (142). وقال ابن حجر:هذا حديث صحيح الإصابة (9/15)، و أُخذِت المبالغة في المضمضمة من قوله : أَسْبِغ الوُضُوءَ. "},
        {"text": "المضمضة، والاستنشاق من كفٍّ واحدة. \n\n لحديث عبد الله بن زيد - رضي الله عنه - في صِفة وضوء النَّبي - صلَّى الله عليه وسلَّم - قال :  .... أَدْخَلَ يَدَهُ فَاسْتَخْرَجَهَا، فَمَضْمَضَ وَاسْتَنْشَقَ مِنْ كَفِ وَاحِدَةٍ، فَفَعَلَ ذلِكَ ثَلاَثاً... رواه البخاري برقم (192) ، رواه مسلم برقم (235) . "},
        {"text": "في مسح الرأس تُسَنُّ الصِّفة المسنونة. \n\n وهي أن يبدأ في مسحه لرأسه فيضع يديه في مقدَّم رأسه ، ثم يذهب بهما إلى قِفا رأسه ، ثم يرجعهما للمكان الذي بدأ منه ، والمرأة أيضاً تفعل هذه السُّنَّة بنفس الطريقة ، وما زاد من الشعر عن عنق المرأة فإنه لا يُمسح .ويدلّ عليه :حديث عبد الله بن زيد - رضي الله عنه - في صِفة وضوء النَّبيّ - صلَّى الله عليه وسلَّم - وفيه :  بَدَأَ بِمُقَدَّمِ رَأْسِهِ ثُمَّ ذَهَبَ بِهِمَا إِلَى قَفَاهُ، ثُمَّ رَدَّهُمَا حَتَّى رَجَعَ إِلَى الْمَكَانِ الَّذِي بَدَأَ مِنْهُ . رواه البخاري برقم (185) ، رواه مسلم برقم (235) ."},
        {"text": "التثليث في غسل الأعضاء . \n\nالغَسْلَة الأولى واجبة ، وأمَّا الثانية ، والثالثة فهي سُنَّة ، ولا يُزاد على ثلاث .ويدلّ عليه :ما ثبت عند البخاري - رحمه الله - من حديث ابن عباس - رضي الله عنهما - : أنَّ النَّبيّ - صَلَّى اللَّهُ عَلَيْهِ وَسَلَّمَ - تَوَضَأَ مَرَّة ، مرَّة رواه البخاري برقم (157)، وثبت عند البخاري أيضا من حديث عبد الله بن زيد - رضي الله عنه - : أَنَّ النَّبِيَّ - صَلَّى اللَّهُ عَلَيْهِ وَسَلَّمَ - تَوَضَّأَ مَرَّتَيْنِ ،مَرَّتَيْنِ رواه البخاري برقم (158)، وثبت في الصحيحين من حديث عثمان - رضي الله عنه – : أنَّ النَّبيّ - صلَّى الله عليه وسلَّم - توضأ ثلاثا رواه البخاري برقم (159)، ولذا فمن الأفضل التنويع أحياناً ، فأحياناً يتوضأ مرَّة ، مرَّة ، وأحياناً مرَّتين ، مرَّتين ، وأحياناً ثلاثاً ، ثلاثاً ، وأحياناً يخالف في العدد، فيغسل مثلاً الوجه ثلاثاً ، واليدين مرتين ، والقدمين مرَّة ،كما في الصحيحين من حديث عبد الله بن زيد - رضي الله عنه - في رواية أخرى انظر : زاد المعاد (1 / 192)، ولكن الأغلب أن يأتي بالكمال ثلاثاً ، ثلاثاً ، فهو هدي النَّبي - صلَّى الله عليه وسلَّم - . "},
        {"text": "الدعاء الوارد بعد الوضوء. \n\n عن عمر - رضي الله عنه -  قال : قال رسول الله - صلَّى الله عليه وسلَّم:  مَا مِنْكُمْ مِنْ أَحَدٍ يَتَوَضَأُ فَيُبْلِغُ - أَوْ فَيُسْبِغُ - الْوُضُوءَ ثُمَّ يَقُولُ: أَشْهَدُ أَنَّ لاَ إِلهَ أَلاَّ اللّهُ ، وَأَنَّ مُحمَّداً عَبْدُ اللّهِ وَرَسُولُهُ ، إلاَّ فُتِحَتْ لَهُ أَبْوَابُ الْجَنَّةِ الثَّمَانِيَةُ، يَدْخُلُ مِنْ أَيِّهَا شَاءَ رواه مسلم برقم (234).أو : ما جاء في حديث أبي سعيد - رضي الله عنه - مرفوعا ً:  من توضأ ففرغ من وضوئه فقال: سُبْحَانَكَ اللَّهُمَّ وَبِحَمْدِكَ، أَشْهَدُ أَنْ لا إِلَهَ إلاَّ أَنْتَ، أَسْتَغْفِرُكَ وأَتُوبُ إلَيْكَ طَبَعَ اللهُ عَلَيْهَا بِطَابِع (الطابع : بفتح الباء وكسرها، لغتان فصيحتان، وهو: الخاتم، ومعنى طَبَعَ: خَتَمَ) ثُمَّ رُفِعَتْ تَحْتَ الْعَرْش فَلَمْ تُكْسَر إِلَى يَوْمِ القِيَامَةِ  رواه النسائي في عمل اليوم والليلة (ص147) ، رواه الحاكم (1/752)، وصحح إسناده ابن حجر-رحمه الله-  انظر : نتائج الأفكار ( 1/246 )، وبيَّن أنه إن لم يصحّ مرفوعاً فهو موقوف، ولن يضره ذلك ؛ لأن له حكم الرفع ، لأنه مما لا مجال فيه للرأي ."}

    ],
    "azaan": [
        {"text": "متابعة المؤذِّن . \n\n يُسَنَّ لمن سمع الأذان أن يقول مثل ما يقول المؤذِّن ، إلا في الحيعلتين ، فيقول:  لا حول ولا قوة إلا بالله  .لحديث عبد اللّه بن عمرو بن العاص - رضي الله عنهما - أَنَّهُ سمع النَّبيَّ - صلَّى الله عليه وسلَّم - يَقُولُ: إِذَا سَمِعْتُمُ الْمُؤَذِّنَ فَقُولُوا مِثْلَ مَا يَقُولُ ... رواه مسلم برقم (384)، وحديث عمر بن الخطاب - رضي الله عنه-  قال: قال رسول اللّه - صلَّى الله عليه وسلم- :  إِذَا قَالَ الْمُؤَذِّنُ: اللّهُ أَكْبَرُ اللّهُ أَكْبَرُ. فَقَالَ أَحَدُكُمْ: اللّهُ أَكْبَرُ الله أَكْبَرُ. ثُمَّ قَالَ: أَشْهَدُ أَنْ لاَ إِلهَ إِلاَّ اللّهُ. قَالَ: أَشْهَدُ أَنْ لاَ إِلهَ إِلاَّ الله. ثُمَّ قَالَ: أَشْهَدُ أَنَّ مُحَمَّداً رَسُولُ اللّهِ. قَالَ: أَشْهَدُ أَنَّ مُحَمَّداً رَسُولُ اللّهِ. ثُمَّ قَالَ: حَيَّ عَلَى الصَّلاَةِ. قَالَ: لاَ حَوْلَ وَلاَ قُوَّةَ إِلاَّ بالله. ثُمَّ قَالَ: حَيَّ عَلَى الْفَلاَحِ. قَالَ: لاَ حَوْلَ وَلاَ قُوَّةَ إِلاَّ بِالله. ثُمَّ قَالَ: الله أَكْبَرُ الله أَكْبَرُ. قَالَ: الله أَكْبَرُ الله أَكْبَرُ. ثُمَّ قَالَ: لاَ إِلهَ إِلاَّ الله. قَالَ: لاَ إِلهَ إِلاَّ الله، مِنْ قَلْبِهِ دَخَلَ الْجَنَّةَ. رواه مسلم برقم (385) .عند التثويب لصلاة الفجر، فإنه من تابع الأذان يقول مثل ما يقول المؤذن:  الصلاة خير من النوم  ."},
        {"text": "قول الذِّكر المخصوص بعد الشهادتين. \n\n يُسَنّ أن يقال بعد ما يقول المؤذن :  أشهد أن محمداً رسول الله  الثانية ، ما جاء في حديث سعد - رضي الله عنه - عن رسول الله - صلَّى الله عليه وسلَّم - أنه قال :  مَنْ قَالَ حِينَ يَسْمَعُ الْمُؤَذِّنَ: أَشْهَدُ أَنْ لاَ إِلهَ إِلاَّ الله وَحْدَهُ لاَ شَرِيكَ لَهُ، وَأَنَّ مُحَمَّداً عَبْدُهُ وَرَسُولُهُ، رَضِيتُ بِالله رَبَّاً ، وَبِمُحَمَّدٍ رَسُولاً ، وَبِالإِسْلاَمِ دِيناً، غُفِرَ لَهُ ذَنْبُهُ . رواه مسلم برقم (386) ."},
        {"text": "الصلاة على النَّبيِّ - صلَّى الله عليه وسلَّم - بعد الأذان . \n\n لحديث عبد الله بن عمرو - رضي الله عنهما -  قال : قال رسول الله - صلَّى الله عليه وسلَّم - : إِذَا سَمِعْتُمُ الْمُؤَذِّنَ فَقُولُوا مِثْلَ مَا يَقُولُ، ثُمَّ صَلُّوا عَلَيَّ ، فَإِنَّهُ مَنْ صَلَّى عَلَيَّ صَلاَةً صَلَّى الله عَلَيْهِ بِهَا عَشْراً، ثُمَّ سَلُوا الله لِي الْوَسِيلَةَ، فَإِنَّهَا مَنْزِلَةٌ فِي الْجَنَّةِ لاَ تَنْبَغِي إِلاَّ لِعَبْدٍ مِنْ عِبَادِ الله، وَأَرْجُو أَنْ أَكُونَ أَنَا هُوَ، فَمَنْ سَأَلَ لِيَ الْوَسِيلَةَ حَلَّتْ له الشَّفَاعَةُ. رواه مسلم برقم (384) .وأفضل أنواع الصلاة :الصلاة الإبراهيمية :  اللهم صلِّ على محمد وعلى آل محمد ،كما صليت على إبراهيم...."},
        {"text": "قول الدعاء الوارد بعد الأذان. \n\n لحديث جابر- رضي الله عنه - قال : قال رسول الله - صلَّى الله عليه وسلَّم - :  مَنْ قَالَ حِينَ يَسْمَعُ النِّدَاءَ : اللَّهُمَّ رَبَّ هَذِهِ الدَّعْوَةِ التَّامَّةِ، وَالصَّلَاةِ الْقَائِمَةِ ، آتِ مُحَمَّدًا الْوَسِيلَةَ وَالْفَضِيلَةَ ، وَابْعَثْهُ مَقَامًا مَحْمُودًا الَّذِي وَعَدْتَهُ ، حَلَّتْ لَهُ شَفَاعَتِي يَوْمَ الْقِيَامَةِ . رواه البخاري برقم (614)."},
        {"text": "الدعاء بعد الأذان. \n\n لحديث عبد الله بن عمرو - رضي الله عنهما - :  أَنَّ رَجُلاً قال: يَا رسولَ الله إِنَّ المُؤَذِّنِينَ يَفْضُلُونَنَا، فقال رسولُ الله - صلَّى الله عليه وسلَّم -: قُلْ كَمَا يَقُولُونَ فإِذَا انْتَهَيْتُ فَسَلْ تُعْطَهُ. رواه أبو داود برقم (524) ، وحسنه ابن حجر (نتائج الأفكار 1/367) ، والألباني (صحيح الكلم الطيب ص 73).ولحديث أنس - رضي الله عنه - أنَّ النَّبيّ - صلَّى الله عليه وسلَّم - قال: الدُعَاءُ بَيْنَ الأَذَانِ وَالإقَامَةِ لا يُرَدّ . رواه النسائي برقم (9895) ، وصححه ابن خزيمة (1/221/425) .فائدة : الخروج من المسجد بعد الأذان منهي عنه .ويدلّ عليه : ما رواه مسلم من حديث أبي الشَّعثاءِ - رضي الله عنه- قال: كُنَّا قُعُوداً فِي الْمَسْجِدِ مَعَ أَبِي هُرَيْرَةَ -رَضِيَ اللهُ عَنَه - فَأَذَّنَ الْمُؤَذِّنُ، فَقَامَ رَجُلٌ مِنَ الْمَسْجِدِ يَمْشِي، فَأَتْبَعَهُ أَبُو هُرَيْرَةَ - رَضِيَ الله عَنَه - بَصَرَهُ حَتَّى خَرَجَ مِنَ الْمَسْجِدِ، فَقَالَ أَبُو هُرَيْرَةَ - رَضِيَ اللهُ عَنَهُ - : أَمَّا هَـذَا فَقَدْ عَصَى أَبَا الْقَاسِمِ - صَلَّى اللَّهُ عَلَيْهِ وَسَلَّمَ -. رواه مسلم برقم (655)."}

    ],

    "mazjed": [
        {"text": "يُسَنُّ التبكير بالذهاب إلى المسجد. \n\n لحديث أبي هريرة - رضي الله عنه - قال : قال رسول الله - صلَّى الله عليه وسلَّم- :  لَوْ يَعْلَمُونَ مَا فِي التَّهْجِيرِ لاَسْتَبَقُوا إِلَيْهِ. رواه البخاري برقم (615) ، رواه مسلم برقم (437).  والتهجير : هو التبكير للصلاة . "},
        {"text": "أن يخرج من بيته متطهراً ؛ لتكتب خطاه. \n\n لحديث أبي هريرة - رضي الله عنه -  قال: قال رسول اللّه - صلَّى الله عليه وسلَّم - : صَلاَةُ الرَّجُلِ فِي جَمَاعَةٍ تَزِيدُ عَلَى صَلاَتِهِ فِي بَيْتِهِ، وَصَلاَتِهِ فِي سُوقِهِ، بِضْعاً وَعِشْرِينَ دَرَجَةً ، وَذلِكَ أَنَّ أَحَدَهُمْ إِذَا تَوَضَّأَ فَأَحْسَنَ الْوُضُوءَ ثُمَّ أَتَى الْمَسْجِدَ، لاَ يَنْهَزُهُ إِلاَّ الصَّلاَةُ، لاَ يُرِيدُ إِلاَّ الصَّلاَةَ ، فَلَمْ يَخْطُ خَطْوَةً إِلاَّ رُفِعَ لَهُ بِهَا دَرَجَةٌ ، وَحُطَّ عَنْهُ بِهَا خَطِيئَةٌ ، حَتَّى يَدْخُلَ الْمَسْجِدَ ، فَإِذَا دَخَلَ الْمَسْجِدَ كَانَ فِي الصَّلاَةِ مَا كَانَتِ الصَّلاَةُ هِيَ تَحْبِسُهُ ، وَالْمَلاَئِكَةُ يُصَلُّونَ عَلَى أَحَدِكُمْ مَا دَامَ فِي مَجْلِسِهِ الَّذِي صَلَّى فِيهِ ، يَقُولُونَ: اللَّهُمَّ ارْحَمْهُ ، اللَّهُمَّ اغْفِرْ لَهُ ، اللّهُمَّ تُبْ عَلَيْهِ ، مَا لَمْ يُؤْذِ فِيهِ ، مَا لَمْ يُحْدِثْ فِيهِ . رواه مسلم برقم (649) "},
        {"text": "أن يخرج إلى الصلاة بسكينة، ووقار \n\n لحديث أبي هريرة - رضي الله عنه - عن النبيِّ - صلَّى الله عليه وسلَّم - قال: إِذَا سَمِعْتُمْ الْإِقَامَةَ فَامْشُوا إِلَى الصَّلَاةِ ، وَعَلَيْكُمْ بِالسَّكِينَةِ وَالْوَقَارِ ، وَلَا تُسْرِعُوا فَمَا أَدْرَكْتُمْ فَصَلُّوا ، وَمَا فَاتَكُمْ فَأَتِمُّوا . رواه البخاري برقم (636) ، رواه مسلم برقم (602) .قال النووي -رحمه الله -:  ... السكينة : التأنَّي في الحركات، واجتناب العبث، والوقار : في الهيئة كغض الطرف ، وخفض الصوت ، وعدم الالتفات. شرح مسلم للنووي، حديث(602) ، باب استحباب إتيان الصلاة بوقار، وسكينة، والنهي عن إتيانها سعياً."},
        {"text": "تقديم الرجل اليمنى عند دخول المسجد، وتقديم اليسرى عند الخروج منه \n\n لحديث أنس - رضي الله عنه - أنه قال : من السُّنَّة إذا دخلت المسجد أن تبدأ برجلك اليمنى ، وإذا خرجت أن تبدأ برجلك اليسرى رواه الحاكم (1/338) ، وصححه على شرط مسلم."},
        {"text": "أن يقول الذِّكر الوارد عند دخول المسجد، وعند الخروج منه \n\n لحديث أبي حميد ، أو أبي أسيد قال: قال رسول اللّه - صلَّى الله عليه وسلَّم- :  إِذَا دَخَلَ أَحَدُكُمْ الْمَسْجِدَ، فَلْيَقُلِ: اللّهُمَّ افْتَحْ لِي أَبْوَابَ رَحْمَتِكَ ، وَإِذَا خَرَجَ ، فَلْيَقُلِ: اللّهُمَّ إِنِّي أَسْأَلُكَ مِنْ فَضْلِكَ . رواه مسلم برقم (713) ."},
        {"text": "أن يُصلِّي ركعتين تحية للمسجد. \n\n وهذا إذا جاء مبكراً للصلاة ، فإنه يُسَنّ له ألّا يجلس حتى يصلِّي ركعتين ؛ لحديث أبي قتادة - رضي الله عنه - قال: قال النَّبيُّ - صلَّى الله عليه وسلَّم- :  إِذَا دَخَلَ أَحَدُكُمْ الْمَسْجِدَ فَلَا يَجْلِسْ حَتَّى يُصَلِّيَ رَكْعَتَيْنِ. رواه البخاري برقم (1163) ، رواه مسلم برقم (714).ويكفي عن تحية المسجد السُّنَّة القَبْلِية للصلاة إن كان لها سُنَّة قبلية كالفجر، والظهر ، أو سُنَّة الضحى إن دخل المسجد ضحى ، أو الوتر إن صلَّاه في المسجد ، أو الفرض ؛ لأن المقصود من تحية المسجد : ألَّا يجلس حتى يُصلِّي ؛ لِمَا في ذلك من عمارة المساجد بالصَّلاة ؛ لئلا يرتادها من غير صلاة."},
        {"text": "يُسَن للرجال المبادرة إلى الصَّف الأول \n\n يُسَن للرجال المبادرة إلى الصَّف الأول ، فهو أفضل الصفوف ، وللنِّساء أفضلها آخرها .لحديث أبي هريرة - رضي الله عنه - أنَّ النَّبيّ - صلَّى الله عليه وسلَّم -  قال:  خَيْرُ صُفُوفِ الرِّجَالِ أَوَّلُهَا، وَشَرُّهَا آخِرُهَا، وَخَيْرُ صُفُوفِ النِّسَاءِ آخِرُهَا، وَشَرُّهَا أَوَّلُهَا رواه مسلم برقم (440)، خيرها ، أي: أكثرها ثواباً وفضلاً ، وشرها ، أي: أقلّها ثواباً وفضلاً.وهذا الحديث فيما إذا صلَّى الرجال والنَّساء جماعة ، وليس بينهما حائل من جدار ونحوه ، فتكون خير صفوف النساء آخرها ؛ لأنه أسترُ لهنَّ عن أعين الرجال ، وأمَّا إذا كان بينهما حائل كجدار ونحوه ، أو كما يكون في كثير من مساجدنا اليوم بأن يُخصَّص للنساء مُصلَّى مستقل ففي هذه الحالة تكون أفضل صفوف النِّساء أولها ؛ لانتفاء عِلَّة القُرب من الرِّجال ؛ لأنَّ الحكم يدور مع عِلَّته وجوداً وعدما ، ولعموم فضل الصَّف الأول في أحاديثٍ منها:حديث أبي هريرة - رضي الله عنه- أَنَّ رسول اللّه - صلَّى الله عليه وسلَّم- قال: لَوْ يَعْلَمُ النَّاسُ مَا فِي النِّدَاءِ وَالصَّفِّ الأَوَّل ، ثُمَّ لَمْ يَجِدُوا إِلاَّ أَنْ يَسْتَهِمُوا عَلَيْهِ لاَسْتَهَمُوا، وَلَوْ يَعْلَمُونَ مَا فِي التَّهْجِيرِ لاَسْتَبَقُوا إِلَيْهِ ، وَلَوْ يَعْلَمُونَ مَا فِي الْعَتَمَةِ - أي : العِشَاء- وَالصُّبْحِ، لأَتَوْهُمَا وَلَوْ حَبْواً  رواه البخاري برقم (615) ، رواه مسلم برقم (437)."},
        {"text": "يُسَنُّ للمأموم أن يكون قريباً من إمامه. \n\n فالأفضل في حقِّ المأموم من حيث اصطفافه للصَّلاة الصف الأول كما تقدَّم، ثُم يحرص أن يكون قريباً من الإمام ، فالأقرب من الجهتين اليمنى أو اليسرى هو الأفضل. ويدلّ عليه :حديث عبد اللّه بن مسعود - رضي الله عنه - قال: قال رسول اللّه - صلَّى الله عليه وسلَّم -: ليَلِنِي مِنْكُمْ أُولُو الأَحْلاَمِ وَالنُّهَى رواه أبو داود برقم (674) ، رواه الترمذي برقم (228) ، فقوله :  ليَلِنِي  أي : ليقترب مني ،  وفي هذا دليل على أنَّ القرب من الإمام مطلوب في أي جهة كان ."}

    ],

        "salah": [
        {"text": "السترة وعددها (4) سنن \n\n (1) يُسَنُّ اتخاذ السترة . \n\n  والسترة سُنَّة للإمام والمنفرد ، وأمَّا المأموم فسترة الإمام سترة له ، فاتخاذ السترة سُنَّة .لحديث أبي سعيد الخدري - رضي الله عنه - مرفوعاً ، وفيه : إِذَا صَلَّى أَحَدُكُمْ إِلَى شَيْءٍ يَسْتُرُهُ مِنَ النَّاسِ... رواه البخاري برقم (509) ، رواه مسلم برقم (505).  والأحاديث في سنيَّة السترة كثيرة فقد استتر النَّبيُّ بالسرير ، والجدار ، والجذع ، والخشبة ، والحربة ، والعَنَزَة ، والراحلة، وغير ذلك .والسترة مشروعة في العمران والفضاء ، في الحضر والسَّفَر ، سواءً خشي ماراً أولم يخشَ ؛ لأن الأحاديث لم تفرِّق بين العمران والفضاء ؛ ولأنَّ النبي - صلَّى الله عليه وسلَّم - كان يستتر في حضره وسفره ، كما في حديث أبي جحيفة- رضي الله عنه -. رواه البخاري برقم (501) ،  رواه مسلم برقم (503) ."},
        {"text": "(2) يُسنُّ الدنو من السترة. \n\n وإذا دنا من السترة؛ فإن السُّنَّة أن يكون بين موضع سجوده وبين السُّترة قدر ممر الشَّاة.لحديث سهل بن سعد السَّاعدي - رضي الله عنه - قال: كَانَ بَيْنَ مُصَلَّى رَسُولِ اللّهِ - صَلَّى اللَّهُ عَلَيْهِ وَسَلَّمَ - وَبَيْنَ الْجِدَارِ مَمَرُّ الشَّاةِ رواه البخاري برقم (496) ، رواه مسلم برقم (508) ، والمقصود بالمُصلَّى هو: موضع سجوده - صلَّى الله عليه وسلَّم - وجاء عند أحمد ، وأبي داود أنَّ بينه وبين السترة ثلاثة أذرع - رواه أحمد برقم (6231) ، وأبو داود برقم (2024)، وصححه الألباني (صحيح ابي داود 6/263) وأصله في البخاري برقم (506)، وهذا باعتبار إذا وقف يكون بينهما كذلك."},
        {"text": "(3) يُسَنُّ ردُّ المارّ بين يدي المصلِّي. \n\nلحديث أبي سعيد - رضي الله عنه- قال : قال رسول الله - صلَّى الله عليه وسلَّم - : إِذَا صَلَّى أَحَدُكُمْ إِلَى شَيْءٍ يَسْتُرُهُ مِنَ النَّاسِ، فَأَرَادَ أحد أَنْ يَجْتَازَ بَيْنَ يَدَيْهِ، فَلْيَدْفَعْ فِي نَحْرِهِ ، فَإِنْ أَبَى فَلْيُقَاتِلْهُ ، فَإِنَّمَا هُوَ شَيْطَانٌ رواه مسلم برقم (505).وأمَّا إذا كان المارّ بين يدي المصلِّي امرأة ، أو كلب أسود ، أو حمار فإنه يجب دفعه على الصحيح؛ لأنها تقطع الصلاة كما في حديث أبي ذر -رضي الله عنه- رواه مسلم برقم (510)، بخلاف غيرها فإنه لا يقطع الصلاة، واختاره شيخنا ابن عثيمين رحمه الله. "},
        {"text": "(4) يُسَنّ التسوك عند كل صلاة . \n\n ويدلّ عليه :حديث أبي هريرة - رضي الله عنه -  أَنَّ رسول الله - صلَّى الله عليه وسلَّم- قال:  لَوْلَا أَنْ أَشُقَّ عَلَى أُمَّتِي أَوْ عَلَى النَّاسِ لَأَمَرْتُهُمْ بِالسِّوَاكِ مَعَ كُلِّ صَلَاةٍ  رواه البخاري برقم (887) ."},
        {"text": "سنن القيام وعددها (10) سنن \n\n (1) رفع اليدين عند تكبيرة الإحرام . \n\n لحديث ابن عمر - رضي الله عنهما -: أَنَّ رَسُولَ اللهِ- صَلَّى اللَّهُ عَلَيْهِ وَسَلَّمَ - كانَ يَرْفَعُ يديه حَذْوَ مَنكِبيهِ إذا افتَتحَ الصلاةَ ، وإذا كَبَّرَ  للرُّكوعِ ، وإذا رَفعَ رأْسَهُ منَ الرُّكوعِ رفَعَهما أَيضاً وقال: سَمعَ اللّهُ لمن حَمِده ربَّنا ولكَ الحمدُ، وكان لا يَفعلُ ذلكَ في السُّجودِ رواه البخاري برقم (735)، رواه مسلم برقم (390).قال ابن هبيرة - رحمه الله - : وأجمعوا على أنَّ رفع اليدين عند تكبيرة الإحرام سُنَّة ، وليس بواجب انظر : الإفصاح (1/123) . ومواضع رفع اليدين التي وردت فيها النصوص أربعة مواضع :- عند تكبيرة الإحرام.- وعند الركوع.- وعند الرفع منه.وهذه الثلاثة ثابتة في الصحيحين عن ابن عمر - رضي الله عنهما - أَنَّ رَسُولَ اللهِ- صَلَّى اللَّهُ عَلَيْهِ وَسَلَّمَ - كانَ يَرْفَعُ يديه حَذْوَ مَنكِبيهِ إذا افتَتحَ الصلاةَ ، وإذا كَبَّرَ  للرُّكوعِ ، وإذا رَفعَ رأْسَهُ منَ الرُّكوعِ رفَعَهما أَيضاً وقال: سَمعَ اللّهُ لمن حَمِده ربَّنا ولكَ الحمدُ، وكان لا يَفعلُ ذلكَ في السُّجودِ رواه البخاري برقم (735)، رواه مسلم برقم (390).والموضع الرابع : عند القيام من التشهد الأول، وهذا ثابت عن ابن عمر - رضي الله عنهما-  أيضاً في صحيح البخاري."},
        {"text": "(2) يُسَنُّ عند رفع اليدين أن تكون الأصابع ممدودة. \n\n لحديث أبي هريرة - رضي الله عنه - قال : أَنَّ النَّبِيَّ - صَلَّى اللَّهُ عَلَيْهِ وَسَلَّمَ - كَانَ إِذَا قَامَ إِلَى الصَّلَاةِ رَفَعَ يَدَيْهِ مَدًّا رواه أحمد برقم (8875)، وأبو داود برقم (753) ، والترمذي برقم (240)، وصححه الألباني (صحيح أبي 3/341)."},
        {"text": "(3) يُسَنُّ أن يكون رفع اليدين إلى الموضع المسنون. \n\n وجاءت النصوص بوجهين عن النَّبيِّ - صلَّى الله عليه وسلَّم- في حدِّ رفع اليدين ، فقد جاء حذو المنكبين في الصحيحين عن ابن عمر - رضي الله عنهما – رواه البخاري برقم (735)، ومسلم برقم (390)، وجاء حذو فروع الأذنين - أي : حذو عوالي الأذنين - عند مسلم ، من حديث مالك بن الحويرث - رضي الله عنه - رواه مسلم برقم (391)، فيُنوِّع المصلِّي تارة يفعل هذه ، وتارة هذه ."},
        {"text": "(4) يُسَنُّ للمصلي بعد تكبيرة الإحرام أن يضع يدَه اليمنى على اليسرى. \n\n وهذا بإجماع أهل العلم ، كما نقله ابن هبيرة - رحم الله الجميع - انظر : الإفصاح ( 1/124 )."},
        {"text": "(5) يُسَنُّ أن يقبض بيده اليمنى اليدَ اليسرى . \n\n الصِّفَة الأولى : يضع يده اليمنى على يده اليسرى ؛ لحديث وائل بن حجر - رضي الله عنه - قال :  رَأَيْتُ رَسُولَ اللَّهِ - صَلَّى اللَّهُ عَلَيْهِ وَسَلَّمَ - إذَا كَانَ قَائِمًا فِي الصَّلاةِ ، قَبَضَ بِـيَمِينِهِ عَلَى شِمَالِهِ. رواه أبو داود برقم (755)، رواه النَّسائي برقم (888) ، وصححه الألباني .والصِّفَة الثانية : أن يضع اليد اليمنى على الذراع اليسرى ؛ لحديث سهل بن سعد - رضي الله عنه - قال :  كَانَ النَّاسُ يُؤْمَرُونَ أَنْ يَضَعَ الرَّجُلُ الْيَدَ الْيُمْنَى ، عَلَى ذِرَاعِهِ الْيُسْرَى فِي الصَّلَاةِ  رواه البخاري برقم (740) .فهو مرَّة يضعها على اليد ، ومرَّة على الذراع ؛ لينوِّع في تطبيق السُّنَّة ."},
        {"text": "(6) يُسَنُّ أن يقول دعاء الاستفتاح. \n\n ولدعاء الاستفتاح عِدَّة صيغ ، يُستحب أن يُنوِّع بينها ، فمرَّة يأتي بهذه الصِّيغة ، ومرَّة بهذه ، وممِّا ورد :أ.  سُبْحَانَكَ اللَّهُمَّ وَبِحَمْدِكَ ، تَبَارَكَ اسْمُكَ وَتَعَالَى جَدُّكَ ، وَلاَ إِلهَ غَيْرُكَ  - رواه أحمد برقم (11473)، وأبو داود برقم (776) ، والترمذي (243) ، والنَّسائي (900) ، من حديث أبي سعيد - رضي الله عنه -، والحديث فيه مقال وله طرق يتقوى بها، وقد حسنه ابن حجر (نتائج (الأفكار1/412) ، وجاء عند مسلم أنَّ عمر - رضي الله عنه - كان يجهر به ؛ ليعلمه الصحابة - رضي الله عنهم أجمعين - رواه مسلم برقم (399) .ب.  الْحَمْدُ للّهِ حَمْداً كَثِيراً طَيِّباً مُبَارَكاً فِيهِ  ، وفي فضله قال رسول الله - صلَّى الله عليه وسلَّم- :  لَقَدْ رَأَيْتُ اثْنَيْ عَشَرَ مَلَكاً يَبْتَدِرُونَهَا. أَيُّهُمْ يَرْفَعُهَا رواه مسلم برقم (600) ، من حديث أنس - رضي الله عنه -. ج .اللَّهُمَّ بَاعِدْ بَيْنِي وَبَيْنَ خَطَايَايَ كَمَا بَاعَدْتَ بَيْنَ الْمَشْرِقِ وَالْمَغْرِبِ، اللَّهُمَّ نَقِّنِي مِنْ خَطَايَايَ كَمَا يُنَقَّى الثَّوْبُ الأَبْيَضُ مِنَ الدَّنَسِ، اللَّهُمَّ اغْسِلْنِي مِنْ خَطَايَايَ بِالثَّلْجِ وَالْمَاءِ وَالْبَرَدِ رواه البخاري برقم (744)، رواه مسلم برقم (598)، من حديث أبي هريرة -رضي الله عنه- .د.  اللّهُ أَكْبَرُ كَبِيراً ، وَالْحَمْدُ للّهِ كَثِيراً ، وَسُبْحَانَ اللّهِ بُكْرَةً وَأَصِيلاً  ، وفي فضله قال رسول الله - صلَّى الله عليه وسلم- :  عَجِبْتُ لَهَا ، فُتِحَتْ لَهَا أَبْوَابُ السَّمَاءِ رواه مسلم برقم (601) ، من حديث ابن عمر - رضي الله عنهما -."},
        {"text": "(7) الاستعاذة. \n\n والاستعاذة سُنَّة ، ويُسَنُّ أن يُنوِّع في صيغ الاستعاذة ، فمرَّة يأتي بهذه ، ومرَّة هذه ومما ورد :أ.  أعوذ بالله من الشيطان الرجيم .وهي الصِّفَة التي اختارها جمهور العلماء - رحمهم الله - ؛ لقوله تعالى:{فَإِذَا قَرَأْتَ الْقُرْآنَ فَاسْتَعِذْ بِاللّهِ مِنَ الشَّيْطَانِ الرَّجِيمِ} [النحل : 98].ب.  أعوذ بالله السميع العليم من الشيطان الرجيم .لقوله تعالى : {وَإِمَّا يَنزَغَنَّكَ مِنَ الشَّيْطَانِ نَزْغٌ فَاسْتَعِذْ بِاللَّهِ إِنَّهُ هُوَ السَّمِيعُ الْعَلِيمُ} [فصلت : 36]."},
        {"text": "(8) البسملة . \n\n فمن السُّنَّة أن يُبسمل بعد الاستعاذة ، فيقول :  بِسْمِ اللَّهِ الرَّحْمنِ الرَّحِيمِ ؛ لحديث نعيم المجمر- رضي الله عنه - قال :  صَلَّيْتُ وَرَاءَ أَبِي هُرَيْرَةَ - رَضِيَ اللهُ عَنَهُ -  فَقَرَأَ: بِسْمِ اللَّهِ الرَّحْمنِ الرَّحِيمِ ، ثُمَّ قَرَأَ بِأُمِّ القُرْآن ... ، وفيه : وَالَّذِي نَفْسِي بِيَدِهِ، إِنِّي لأَشْبَهُكُمْ صَلاةً بِرَسُولِ اللَّهِ - صَلَّى اللَّهُ عَلَيْهِ وَسَلَّمَ-  رواه النَّسَائي برقم (906) ، رواه ابن خزيمة وصححه (1/251)، قال الدارقطني: هذا حديث صحيح ، ورواته كلهم ثقات السنن (2/46).والصَّارف عن الوجوب أيضاً : أنَّ النَّبيّ - صلَّى الله عليه وسلَّم -لم يُعلِّمها المسيء في صلاته ، وإنما أرشده إلى فاتحة الكتاب ،كما في حديث أبي هريرة - رضي الله عنه - المتفق عليه - رواه البخاري برقم (757) ، رواه مسلم برقم (397)."},
        {"text": "(9) التأمين مع الإمام. \n\n وذلك إذا قرأ الإمام الفاتحة في الجهرية فإنَّ من السُّنَّة أن يؤمِّن المأموم إذا أمَّن الإمام ؛ لحديث أبي هريرة - رضي الله عنه- أنَّ النَّبيّ - صلَّى الله عليه وسلَّم-  قال:إِذَا أَمَّنَ الإِمَامُ فَأَمِّنُوا ، فإِنَّهُ مَنْ وَافَقَ تَأْمِينُهُ تَأْمِينَ الْمَلاَئِكَةِ، غُفِرَ لَهُ مَا تَقَدَّمَ مِنْ ذَنْبِهِ رواه البخاري برقم (780) ، رواه مسلم برقم (410)."},
        {"text": "(10) قراءة السورة التي بعد الفاتحة. \n\n فقراءتها سُنَّة في الركعتين الأولى ، والثانية ، وهو قول جمهور العلماء - رحمهم الله - ؛ لحديث أبي قتادة - رضي الله عنه - قال:  كَانَ النَّبِيُّ - صَلَّى اللَّهُ عَلَيْهِ وَسَلَّمَ- يَقْرَأُ فِي الرَّكْعَتَيْنِ الْأُولَيَيْنِ مِنْ صَلَاةِ الظُّهْرِ بِفَاتِحَةِ الْكِتَابِ ، وَسُورَتَيْنِ يُطَوِّلُ فِي الْأُولَى وَيُقَصِّرُ فِي الثَّانِيَةِ  رواه البخاري برقم (759)، رواه مسلم برقم (451)  .وأمَّا المأموم في الصلاة الجهرية لا يقرأ السورة التي بعد الفاتحة بل يستمع لإمامه .قال ابن قدامة - رحمه الله - :  لا نعلم بين أهل العلم خلافا في أنه يُسَنَّ قراءة سورة بعد الفاتحة في الركعتين الأوليين من كل صلاة  انظر : المغني (1/568) ."},
        {"text": "سنن الركوع وعددها (4) سنن \n\n (1) يُسَنُّ وضع اليدين على الركبتين، كالقابض عليهما ويُفرِّج الأصابع. \n\n لحديث أبي حميد - رضي الله عنه-  قال :  أَنَا كُنْتُ أَحْفَظَكُمْ لِصَلَاةِ رَسُولِ اللَّهِ - صَلَّى اللَّهُ عَلَيْهِ وَسَلَّمَ - ، رَأَيْتُهُ إِذَا كَبَّرَ جَعَلَ يَدَيْهِ حِذَاءَ مَنْكِبَيْهِ ، وَإِذَا رَكَعَ أَمْكَنَ يَدَيْهِ مِنْ رُكْبَتَيْهِ ، ثُمَّ هَصَرَ ظَهْرَهُ...  رواه البخاري برقم (828) ، وفي حديث أبي مسعود – رضي الله عنه-  :  وَفَرَّجَ بَيْنَ أَصَابِعَهُ مِنْ وَرَاءِ رُكْبَتَيْهِ ...  رواه أحمد برقم (17081) ، و أبو داود برقم (863)، رواه النَّسَائي برقم (1038)، بسند حسن، وله شاهد من حديث وائل بن حجر عند ابن خزيمة (594) ."},
        {"text": "(2) يُسنُّ للراكع أن يمد ظهره مستوياً. \n\n لحديث أبي حميد السَّاعدي - رضي الله عنه - أنَّ رسول الله - صلَّى الله عليه وسلَّم- : وَإِذَا رَكَعَ أَمْكَنَ يَدَيْهِ مِنْ رُكْبَتَيْهِ ، ثُمَّ هَصَرَ ظَهْرَهُ...  رواه البخاري برقم (828) ، و هَصَرَ ظهرَهُ : أي ثناه في استواء من غير تقويس ، وكذلك يُسَنُّ أن يكون رأسه على مستوى رأسه ، فلا يرفعه ولا يخفضه ؛ لحديث عائشة - رضي الله عنها - عند مسلم ، وفيه قالت في وصف ركوع النَّبي - صلَّى الله عليه وسلَّم - : وَكَانَ إِذَا رَكَعَ لَمْ يُشْخِصْ رَأْسَهُ وَلَمْ يُصَوِّبْهُ ، وَلكِنْ بَيْنَ ذلِكَ  رواه مسلم برقم (498).و يُشْخِصْ  : بضم الياء وإسكان الشين : أي :لم يرفعه ، وَلَمْ يُصَوِّبْهُ بضم الياء ، وفتح الصاد: أي: لم يخفضه خفضاً بليغاً ."},
        {"text": "(3) يُسَنّ للمصلِّي عند الركوع أن يجافي مرفقيه عن جنبيه. \n\n أي: يباعد يديه عن جنبيه ؛ لحديث أبي مسعود  - رضي الله عنه - السابق، وفيه :  ثُمَّ رَكَعَ وَجَافَى يَدَيْهِ وَوَضَعَ يَدَيْهِ عَلَى رُكْبَتَيْهِ وَفَرَّجَ بَيْنَ أَصَابِعَهُ... وقال : هَكَذَا رَأَيْتُ رَسُوْلُ اللهِ - صلَّى الله عليه وسلَّم - يُصَلِّي رواه أحمد برقم (17081)، وأبو داود برقم (863)، والنسائي برقم (1038)، انظر : حاشية (2). و(المجافاة) هي : المباعدة ، لكن هذا مشروط فيما إذا لم يؤذِ من كان بجانبه ، فإنه لا ينبغي للمصلِّي أن يفعل سُنَّة يؤذي بها غيره من المصلِّين.قال النووي - رحمه الله -  عن المجافاة :  ولا أعلم في استحبابها خلافاً لأحد من العلماء ، وقد نقل الترمذي استحبابها في الركوع ، والسجود عن أهل العلم مطلقاً  انظر : المجموع (3/410)."},
        {"text": "(4) يُسَنُّ أن يأتي بالأذكار الواردة في الركوع. \n\n فيسنُّ للراكع أن يأتي مع ( سبحان ربي العظيم ) أذكاراً أخرى وردت في الركوع ، وممَّا ورد : أ.  سُبْحَانَكَ اللَّهُمَّ رَبَّنَا وَبِحَمْدِكَ، اللَّهُمَّ اغْفِرْ لِي رواه البخاري برقم (794)، رواه مسلم برقم (484) ، من حديث عائشة -رضي الله عنها- . ب.  سُبُّوحٌ قُدُّوسٌ رَبُّ الْمَلاَئِكَةِ وَالرُّوحِ  رواه مسلم برقم (487)  ، من حديث عائشة - رضي الله عنها - .ج.  اللَّهُمَّ لَكَ رَكَعْتُ ، وَبِكَ آمَنْتُ ، وَلَكَ أَسْلَمْتُ ، خَشَعَ لَكَ سَمْعِي، وَبَصَرِي ، وَمُخِّي ، وَعَظْمِي ،  وَعَصَبِي رواه مسلم برقم (771) ، من حديث علي- رضي الله عنه - .د.  سبحانَ ذِي الجَبَرُوتِ وَالمَلَكوتِ وَالكِبْرِياءِ وَالعَظَمَةِ رواه أحمد برقم (23411)، و أبو داود برقم (873)، ورواه النَّسَائي برقم (1050) من حديث عن عوف بن مالك -رضي الله عنه -، وصححه الألباني (صحيح أبي داود 4/27)."},
        {"text": "الرفع من الركوع وعددها (3) سنن \n\n (1) تطويل هذا الركن . \n\n لحديث ثابت البناني عن أنس - رضي الله عنه - أنه قال :  إِنِّي لاَ آلُو (لا آلو : أي لا أُقصِّر) أَنْ أُصَلِّيَ بِكُمْ كَمَا رَأَيْتُ رَسُولَ اللّهِ - صلَّى الله عليه وسلَّم - يُصَلِّي بِنَا، قَالَ : فَكَانَ أَنَسٌ يَصْنَعُ شَيْئاً لاَ أَرَاكُمْ تَصْنَعُونَهُ، كَانَ إِذَا رَفَعَ رَأْسَهُ مِنَ الرُّكُوعِ انْتَصَبَ قَائِماً، حَتَّى يَقُولَ الْقَائِلُ: قَدْ نَسِيَ ، وَإِذَا رَفَعَ رَأْسَهُ مِنَ السَّجْدَةِ مَكَثَ حَتَّى يَقُولَ الْقَائِلُ: قَدْ نَسِيَ  رواه البخاري برقم (821) ، رواه مسلم برقم (472) ."},
        {"text": "(2)  التنويع في صيغ :  ربنا ولك الحمد . \n\n لتنويع في صيغ :  ربنا ولك الحمد  بين ما يلي :أ.  اللَّهُمَّ رَبَّنَا وَلَكَ الْحَمْدُ  رواه البخاري برقم (795) من حديث أبي هريرة  - رضي الله عنه -.ب.  اللَّهُمَّ رَبَّنَا لَكَ الْحَمْدُ رواه البخاري برقم (796) ، رواه مسلم برقم (404) من حديث أبي هريرة  - رضي الله عنه -.ج.  رَبَّنَا وَلَكَ الْحَمْدُ  رواه البخاري برقم (799) ، رواه مسلم برقم (411) من حديث عائشة  - رضي الله عنها -.د. رَبَّنَا لَكَ الْحَمْدُ  رواه البخاري برقم (722)، من حديث أبي هريرة - رضي الله عنه .فمرَّة يأتي بهذه ، ومرَّة يأتي بهذه ."},
        {"text": "(3) يُسَنُّ أن يأتي بالأذكار الواردة بعد الرفع من الركوع. \n\n ومن الأذكار التي تُشرع بعد الرفع من الركوع ما يلي :أ.  رَبَّنَا لَكَ الْحَمْدُ ، مِلْءُ السَّمَاوَاتِ وَالأَرْضِ ، وَمِلْءُ مَا شِئْتَ مِنْ شَيْءٍ بَعْدُ ، أَهْلُ الثَّنَاءِ وَالْمَجْدِ ، أَحَقُّ مَا قَالَ الْعَبْدُ ، وَكُلُّنَا لَكَ عَبْدٌ ، اللَّهُمَّ لاَ مَانِعَ لِمَا أَعْطَيْتَ ، وَلاَ مُعْطِيَ لِمَا مَنَعْتَ ، وَلاَ يَنْفَعُ ذَا الْجَدِّ مِنْكَ الْجَدُّ رواه مسلم برقم (477) من حديث أبي سعيد - رضي الله عنه - .ب.  الْحَمْدُ للّهِ حَمْداً كَثِيراً طَيِّباً مُبَارَكاً فِيهِ  قال النَّبي - صلَّى الله عليه وسلَّم - عن هذا اللفظ :  لَقَدْ رَأَيْتُ اثْنَيْ عَشَرَ مَلَكاً يَبْتَدِرُونَهَا، أَيُّهُمْ يَرْفَعُهَا رواه مسلم برقم (600) ، ورواه البخاري برقم (799).ج.  اللَّهُمَّ طَهِّرْنِي بِالثَّلْجِ وَالْبَرَدِ وَالْمَاءِ الْبَارِدِ ، اللَّهُمَّ طَهِّرْنِي مِنَ الذُّنُوبِ وَالْخَطَايَا كَمَا يُنَقَّى الثَّوْبُ الأَبْيَضُ مِنَ الْوَسَخِ  رواه مسلم برقم (476) .وإذا أتى المسلم بهذه الأذكار استطاع أن يطيل هذه الركن ."},
        {"text": "سنن السجود وعددها (4) سنن \n\n (1) يُسَنُّ للساجد أن يجافي عضديه عن جنبه، وبطنه عن فخذيه . \n\n لحديث عبد الله بن بحينة - رضي الله عنه - : أَنَّ رَسُولَ اللّهِ - صلَّى الله عليه وسلَّم -كَانَ إِذَا صَلَّى فَرَّجَ بَيْنَ يَدَيْهِ ، حَتَّى يَبْدُوَ بَيَاضُ إِبْطَيْهِ  رواه البخاري برقم (390) ، رواه مسلم برقم (495)، وحديث ميمونة - رضي الله عنها - قالت : كَانَ النَّبِيُّ - صلَّى الله عليه وسلَّم - إِذَا سَجَدَ ، لَوْ شَاءَتْ بَهْمَةٌ (و البَهْمَة : واحدة البَهَم ، وهي أولاد الغنم من الذكور والإناث) أَنْ تَمُرَّ بَيْنَ يَدَيْهِ لَمَرَّتْ  رواه مسلم برقم (496) ، وفي هذا المبالغة في التفريج بين اليدين ، فالسُّنَّة التفريج بين اليدين ما لم يكن في ذلك أذية لمن حوله ،كما مضى في المجافاة في الركوع .ومن السُّنَّة أيضاً إذا سجد المصلِّي أن يفرج بين فخذيه فلا يجمعهما ، وأن لا يحمل بطنه على فخذيه ، بل يباعد فخذيه عن بطنه ؛ لحديث أبي حميد - رضي الله عنه - في صِفة صلاة النَّبيّ - صلَّى الله عليه وسلَّم- :  وَإِذَا سجد فَرَّجَ بَيْنَ فَخِذَيْهِ غَيْرَ حَامِلٍ بَطْنَهُ عَلَى شَيْء مِنْ فَخِذَيْهِ رواه أبو داود برقم (735)، وهو سنة بإجماع أهل العلم كما نقل الشوكاني وغيره . الشوكاني – رحمه الله -  : والحديث يدل على مشروعية التفريج بين الفخذين في السجود ، ورفع البطن عنهما ، ولا خلاف في ذلك  انظر : نيل الأوطار(2/257 ) ."},
        {"text": "(2) يُسَنّ للسَّاجد أن يستقبل بأطراف أصابع رجليه القِبْلَةَ. \n\nلحديث أبي حميد - رضي الله عنهما - أنه قال :  أنا أحفظكم لصلاة رسول الله - صلَّى الله عليه وسلَّم - ، وفيه :  فإذا سَجدَ وضعَ يدَيهِ غيرَ مُفتَرِشٍ ولا قابضِهما ، واستقبَلَ بأَطرافِ أصابعِ رجلَيهِ القِبلةَ  رواه البخاري برقم (828).وأمَّا أصابع اليدين أثناء السجود فالسُّنَّة أن تكون مضمومة ويجعل يديه مستقبلة القبلة ؛ لِمَا ثبت عن ابن عمر - رضي الله عنهما - في موطأ الإمام مالك (انظر : موطأ مالك)، وأيضاً في مصنَّف ابن أبي شيبة عن حفص بن عاصم - رضي الله عنه - قال :  من السُّنَّة في الصلاة أن يبسط كفيه ويضم أصابعه ، ونوجههما مع جهة القِبْلة  انظر : مصنف ابن أبي شيبة (1/236)، وله شاهد من حديث وائل ابن حجر: أن النبي -صلى الله عليه وسلم- كان إذا سجد ضم أصابعه وحسنه الهيثمي (مجمع الزوائد 2/135). "},
        {"text": "(3) يُسَنُّ أن يأتي بالأذكار الواردة في السجود. \n\n فيُسنُّ للساجد أن يأتي مع ( سبحان ربي الأعلى ) أذكاراً أخرى وردت في السجود ، وممَّا ورد :أ.  سُبْحَانَكَ اللَّهُمَّ رَبَّنَا وَبِحَمْدِكَ، اللَّهُمَّ اغْفِرْ لِي رواه البخاري برقم (794) ، رواه مسلم برقم (484) من حديث عائشة - رضي الله عنه -.ب.  سُبُّوحٌ قُدُّوسٌ رَبُّ الْمَلاَئِكَةِ وَالرُّوحِ  رواه مسلم برقم (487)، من حديث عائشة - رضي الله عنه - .ج.  اللَّهُمَّ لَكَ سَجَدْتُ ، وَبِكَ آمَنْتُ ، وَلَكَ أَسْلَمْتُ ، سَجَدَ وَجْهِي لِلَّذِي خَلَقَهُ وَصَوَّرَهُ، وَشَقَّ سَمْعَهُ وَبَصَرَهُ، تَبَارَكَ الله أَحْسَنُ الْخَالِقِينَ  رواه مسلم برقم (771) ، من حديث علي- رضي الله عنه - .د.  اللَّهُمَّ اغْفِرْ لِي ذَنْبِي كُلَّهُ دِقَّهُ وَجِلَّهُ ، وَأَوَّلَهُ وَآخِرَهُ، وَعَلاَنِيَتَهُ وَسِرَّهُ  رواه مسلم برقم (483) ، من حديث أبي هريرة - رضي الله عنه -.ﻫ. اللَّهُمَّ أَعُوذُ بِرِضَاكَ مِنْ سَخَطِكَ ، وَبِمُعَافَاتِكَ مِنْ عُقُوبَتِكَ ، وَأَعُوذُ بِكَ مِنْكَ ، لاَ أُحْصِي ثَنَاءً عَلَيْكَ ، أَنْتَ كَمَا أَثْنَيْتَ عَلَى نَفْسِكَ  رواه مسلم برقم (486) من حديث عائشة - رضي الله عنها - ، فيُسَنُّ أن يأتي بما يستطيع من هذه الأذكار في سجوده وينوِّع بينها ، ومعلوم أنَّ الواجب في الركوع (سبحان ربي العظيم) مرَّة واحدة وما زاد فهو سُنَّة ، وكذا في السجود الواجب قول : (سبحان ربي الأعلى ) مرَّة واحدة ، وأمَّا الثانية ، و الثالثة فسُنَّة ."},
        {"text": "(4) يُسَنُّ الإكثار من الدعاء في السجود. \n\n لأنَّ السجود أقرب موضع للعبد من ربه جلَّ في علاه، فيُسَنُّ أن يُكْثِر من الدعاء فيه ، لقول النَّبيِّ - صلَّى الله عليه وسلَّم - كما في لحديث ابن عباس - رضي الله عنهما - عند مسلم :وَأَمَّا السُّجُودُ فَاجْتَهِدُوا فِي الدُّعَاءِ ، فَقَمِنٌ - ( قَمِنٌ أي: حريٌّ أن يُستجاب له)- ، أَنْ يُسْتَجَابَ لَكُمْ رواه مسلم برقم (479) ."},
        {"text": "سنن الجلسة بعد السجدتين وعددها (3) سنن \n\n (1) من السُّنَّة أن يفرش المصلِّي رجله اليسرى، ويجلس عليها، وينصب اليمنى. \n\n لحديث أبي حميد السَّاعدي - رضي الله عنه - مرفوعاً ، وفيه : فَإِذَا جَلَسَ فِي الرَّكْعَتَيْنِ جَلَسَ عَلَى رِجْلِهِ الْيُسْرَى وَنَصَبَ الْيُمْنَى رواه البخاري برقم (828)."},
        {"text": "(2) تطويل هذا الركن. \n\n لحديث ثابت البناني عن أنس - رضي الله عنه - أنه قال : إِنِّي لاَ آلُو (لا آلو : أي لا أُقصِّر) أَنْ أُصَلِّيَ بِكُمْ كَمَا رَأَيْتُ رَسُولَ اللّهِ - صلَّى الله عليه وسلَّم - يُصَلِّي بِنَا، قَالَ : فَكَانَ أَنَسٌ يَصْنَعُ شَيْئاً لاَ أَرَاكُمْ تَصْنَعُونَهُ، كَانَ إِذَا رَفَعَ رَأْسَهُ مِنَ الرُّكُوعِ انْتَصَبَ قَائِماً، حَتَّى يَقُولَ الْقَائِلُ: قَدْ نَسِيَ ، وَإِذَا رَفَعَ رَأْسَهُ مِنَ السَّجْدَةِ مَكَثَ حَتَّى يَقُولَ الْقَائِلُ: قَدْ نَسِيَ  رواه البخاري برقم (821) ، رواه مسلم برقم (472).  "},
        {"text": "(3) يُسنُّ لمن أراد القيام إلى أي ركعة، ثانية، أو رابعة، أن يجلس يسيراً قبل أن يقوم . \n\n وهذه تسمَّى : ( جلسة الاستراحة ) ، وليس لها ذكر معيَّن.وجاء ثبوتها في ثلاثة أحاديث منها :حديث مالك بن الحويرث - رضي الله عنه - : أَنَّهُ رَأَى النَّبِيَّ - صَلَّى اللَّهُ عَلَيْهِ وَسَلَّمَ - يُصَلِّي فَإِذَا كَانَ فِي وِتْرٍ مِنْ صَلَاتِهِ ، لَمْ يَنْهَضْ حَتَّى يَسْتَوِيَ قَاعِدًا  رواه البخاري برقم (823)، ومالك بن الحويرث - رضي الله عنه - هو الذي نقل قول النَّبيّ - صلَّى الله عليه وسلَّم -: صَلُّوا كَمَا رَأَيْتُمُوْنِيْ أُصَلِّيْ  رواه البخاري برقم (631) .واختُلِف في سنيَّة ( جلسة الاستراحة ) ، والصواب : أنها سُنَّة مطلقاً ؛ لحديث مالك - رضي الله عنه - ، وممن رجَّح سنيَّتها مطلقاً : النووي ، والشوكاني ، وابن باز ، والألباني - رحمهم الله - ، واللجنة الدائمة للبحوث العلمية والإفتاء – (انظر:فتاوى ومقالات متنوعة(11/99)، وفتاوى اللجنة الدائمة (6/445-446)-.وقال النووي - رحمه الله - :  وهذا هو الصواب الذي ثبتت فيه الأحاديث الصحيحة  انظر : المجموع (3/441)."},
        {"text": "سنن التشهد وعددها (8) سنن \n\n (1) يُسَنّ أن يفترش المصلِّي رجله اليسرى في التشهد، وينصب اليمنى. \n\n وهذه الصِّفة يفعلها المصلِّي بعدما يُصلِّي الثانية بركوعها ، وسجودها ، وقيامها ، وقعودها ، سواء كان في صلاة رباعية ، أو ثلاثية ، أو ثنائية ، فأي ركعة ثانية في الجلوس في تشهدها تكون على هذه الصِّفة ؛ لحديث أبي حميد السَّاعدي - رضي الله عنه -  مرفوعاً، وفيه :  فَإِذَا جَلَسَ فِي الرَّكْعَتَيْنِ جَلَسَ عَلَى رِجْلِهِ الْيُسْرَى وَنَصَبَ الْيُمْنَى رواه البخاري برقم (828)، وحديث عائشة - رضي الله عنها - :  وَكَانَ يَقُولُ فِي كُلِّ رَكْعَتَيْنِ التَّحِيَّةَ ، وَكَانَ يَفرشُ رِجْلَهُ الْيُسْرَى وَيَنْصِبُ رِجْلَهُ الْيُمْنَى رواه مسلم برقم (498) .وأمَّا التشهد الأخير في الصَّلاة الرباعية ، والثلاثية فسيأتي بيان صِفته ."},
        {"text": "(2) السُّنَّة أن ينوِّع في وضع اليدين حال التشهد. \n\n ووضع الكفين حال التشهد له صفتان :الصِّفَة الأولى : أن يضع اليدين على الفخذين .الصِّفَة الثانية : أن يضع اليدين على الركبتين ، وذلك بأن يُلْقِمَ يده اليسرى ركبته اليسرى ، وأمَّا اليمنى فيُشير بها - كما سيأتي بيانه - وأمَّا اليسرى فهي مبسوطة دائماً.لحديث ابن عمر - رضي الله عنهما - قال : كَانَ - أي: النَّبي - صلَّى الله عليه وسلَّم - - إِذَا جَلَسَ فِي الصَّلاَةِ، وَضَعَ كَفَّهُ الْيُمْنَى عَلَى فَخِذِهِ الْيُمْنَى، وَقَبَضَ أَصَابِعَهُ كُلَّهَا، وَأَشَارَ بِإِصْبَعِهِ الَّتِي تَلِي الإِبْهَامَ، وَوَضَعَ كَفَّهُ الْيُسْرَى عَلَى فَخِذِهِ الْيُسْرَى رواه مسلم برقم (580)، وفي رواية : وَيُلْقِمُ كَفَّهُ الْيُسْرَى رُكْبَتَهُ  رواه مسلم برقم (579) ."},
        {"text": "(3) السُّنَّة أن ينوِّع في كيفيَّة وضع الأصابع حال التشهد. \n\n ووضع الأصابع حال التشهد له صِفَتان :الصِّفَة الأولى : أن يقبض أصابع كفه اليمنى كلها ، ويُشِير بإصبعه السَّبابة ، واليسرى تكون مبسوطة .لحديث ابن عمر - رضي الله عنهما - السَّابق:  ...قَبَضَ أَصَابِعَهُ كُلَّهَا، وَأَشَارَ بِإِصْبَعِهِ الَّتِي تَلِي الإِبْهَامَ... رواه مسلم برقم (580) .الصِّفة الثانية : أن يعقد ثلاثاً وخمسين ، بأن يقبض الخنصر والبنصر ، ويُحلِّق الإبهام مع الوسطى ، ويُشير بالسبابة ، وأمَّا اليسرى فتكون مبسوطة .لحديث ابن عمر - رضي الله عنهما - السَّابق في رواية : كَانَ - أي : النَّبي صلَّى الله عليه وسلَّم - إِذَا قَعَدَ فِي التَّشَهِّدِ وَضَعَ يَدَهُ الْيُسْرَى عَلَى رُكْبَتِهِ الْيُسْرَى ، وَوَضَعَ يَدَهُ الْيُمْنَى عَلَى رُكْبَتِهِ الْيُمْنَى ، وَعَقَدَ ثَلاَثَةً وَخَمْسِينَ ، وَأَشَارَ بِالسَّبَّابَةِ ، رواه مسلم برقم (580)."},
        {"text": "(4) السُّنَّة أن ينوِّع المصلِّي بين صيغ التشهَّد. \n\n فيفعل هذه الصيغة تارة ، وهذه تارة ، وممّا ورد :أ.  التَّحِيَّاتُ لِلَّهِ ، وَالصَّلَوَاتُ ، وَالطَّيِّبَاتُ ، السَّلَامُ عَلَيْكَ أَيُّهَا النَّبِيُّ وَرَحْمَةُ اللَّهِ وَبَرَكَاتُهُ ، السَّلَامُ عَلَيْنَا وَعَلَى عِبَادِ اللَّهِ الصَّالِحِينَ ، أَشْهَدُ أَنْ لَا إِلَهَ إِلَّا اللَّهُ ، وَأَشْهَدُ أَنَّ مُحَمَّدًا عَبْدُهُ وَرَسُولُهُ  رواه البخاري برقم (1202) ، رواه مسلم برقم (402) من حديث ابن مسعود - رضي الله عنه -.ب.  التَّحِيَّاتُ الْمُبَارَكَاتُ ، الصَّلَوَاتُ الطَّيِّبَاتُ لِلَّهِ ، السَّلاَمُ عَلَيْكَ أَيُّهَا النَّبِيُّ... رواه مسلم برقم (403) من حديث ابن عباس - رضي الله عنهما -.. ثم يُكمل كما سبق .ج.  التَّحِيَّاتُ الطَّيِّبَاتُ الصَّلَوَاتُ لله ، السَّلاَمُ عَلَيْكَ أيُّهَا النَّبِيُّ... رواه مسلم برقم (404) من حديث أبي موسى- رضي الله عنه - ،  ثم يُكمل كما سبق ."},
        {"text": "(5) السُّنَّة أن يجلس المصلِّي في التشهد الأخير مُتَوَرِّكاً في الصلاة الثلاثية، والرباعية. \n\n والمقصود أن يقعد في التشهد الأخير إذا كانت الصلاة رباعية ، أو ثلاثية على مقعدته ، فيقعد على الورك الأيسر ، والتَّورك ورد على أكثر من وجه ، فيُستحب التنويع حينئذ .وممّـا ورد : 1/ أن يفرش رجله اليسرى ، ويخرجها من الجانب الأيمن ، وينصب اليمنى ،  ويجعل مقعدته على الأرض.وهذه الصِّفَة رواها البخاري - رحمه الله -  عن أبي حميد السَّاعدي - رضي الله عنه - رواه البخاري برقم (828) .                                                                              2/ أن يفرش القدمين جميعاً ، ويُخرجهما من الجانب الأيمن ، ويجعل مقعدته على الأرض .وهذه الصِّفة رواها أبو داود برقم (731) ، وابن حبان برقم (1867)، والبيهقي (2/128)  من حديث أبي حميد السَّاعدي - رضي الله عنه - وصحَّحها الألباني - رحم الله الجميع -.وليُعلَم أنَّ التَّورك على الصحيح ليس في كل تشهدٍ أخير ، وإنما في التشهد الأخير في الصلاة الثلاثية ، والرباعية دون الثنائية."},
        {"text": "(6) السُّنَّة أن ينوِّع المصلِّي بين صِيغ الصَّلاة على النَّبيِّ - صلَّى الله عليه وسلَّم- . \n\n فقد وردت عِدَّة صيغ في الصَّلاة على النَّبيِّ - صلَّى الله عليه وسلَّم - ،  فالسُّنَّة أن ينوِّع بينها ، وممّا ورد :أ. اللَّهُمَّ صَلِّ عَلَى مُحَمَّدٍ ، وَعَلَى آلِ مُحَمَّدٍ ،كَمَا صَلَّيْتَ عَلَى إِبْرَاهِيمَ ، وَعَلَى آلِ إِبْرَاهِيمَ إِنَّكَ حَمِيدٌ مَجِيدٌ ، اللَّهُمَّ بَارِكْ عَلَى مُحَمَّدٍ ، وَعَلَى آلِ مُحَمَّدٍ ،كَمَا بَارَكْتَ عَلَى إِبْرَاهِيمَ ،وَعَلَى آلِ إِبْرَاهِيمَ إِنَّكَ حَمِيدٌ مَجِيدٌ  رواه البخاري برقم (3370) من حديث كعب بن عجرة - رضي الله عنه- .ب.  اللَّهُمَّ صَلِّ عَلَى مُحَمَّدٍ وَعَلَى آلِ مُحَمَّد كَمَا صَلَّيْتَ عَلَى آلِ إِبْرَاهِيمَ ، وَبَارِكْ عَلَى مُحَمَّدٍ وَعَلَى آلِ مُحَمَّدٍ كَمَا بَارَكْتَ عَلَى آلِ إِبْرَاهِيمَ ، فِي الْعَالَمِينَ ، إِنَّكَ حَمِيدٌ مَجِيدٌ  رواه مسلم برقم (405) من حديث أبي مسعود الأنصاري - رضي الله عنه - .ج. اللَّهُمَّ صَلِّ عَلى مُحَمَّدٍ وَعَلَى أَزْوَاجِهِ وَذُرِّيَّتِهِ ،كَمَا صَلَّيْتَ عَلَى آلِ إِبْرَاهِيمَ ، وَبَارِكْ عَلَى مُحَمَّدٍ وَعَلَى أَزْوَاجِهِ وَذُرِّيَّتِهِ، كَمَا بَارَكْتَ عَلَى آلِ إِبْرَاهِيمَ ، إِنَّكَ حَمِيدٌ مَجِيدٌ . رواه البخاري برقم (3369)، رواه مسلم برقم (407) من حديث أبي حميد السَّاعدي- رضي الله عنه-. "},
        {"text": "(7) يُسَنُّ أن يستعيذ المصلِّي من أربع قبل أن يُسلِّم . \n\n وهو قول جمهور العلماء - رحمهم الله - ، لحديث أبي هريرة - رضي الله عنه - ، أنَّ النَّبيّ - صلَّى الله عليه وسلَّم - قال : إِذَا فَرَغَ أَحَدُكُمْ مِنَ التَّشَهِّدِ الآخِرِ، فَلْيَتَعَوَّذْ بِاللّهِ مِنْ أَرْبَعٍ: مِنْ عَذَابِ جَهَنَّمَ ، وَمِنْ عَذَابِ الْقَبْرِ، وَمِنْ فِتْنَةِ الْمَحْيَا وَالْمَمَاتِ، وَمِنْ شَرِّ الْمَسِيحِ الدَّجَّالِ رواه مسلم برقم (588) ، رواه البخاري برقم (832) ، رواه مسلم برقم (589) ، من حديث عائشة - رضي الله عنها - ."},
        {"text": "(8) أدعية أخرى يُسَنُّ للمصلِّي أن ينوِّع في الإتيان بها قبل السَّلام \n\n وهناك أدعية أخرى وردت في السُّنَّة ، يُسَنُّ للمصلِّي أن ينوِّع في الإتيان بها قبل السَّلام ، وممّـا ورد : \n\n 1/ اللَّهُمَّ إنِّي أَعُوذُ بِكَ من المأْثَمِ والمغْرَمِ \n\n رواه البخاري برقم 832 ، رواه مسلم برقم 589 \n\n 2/ اللَّهُمَّ إنِّي أَسْأَلُكَ الجَنَّةَ وَأَعَوْذُ بِكَ مِنَ النَّارِ \n\n رواه أبو داود برقم 792، وصحح إسناده الألباني صحيح أبي داود 3/377 \n\n 3/ اللَّهُمَّ إِنِّي ظَلَمْتُ نَفْسِي ظُلْمًا كَثِيرًا وَلَا يَغْفِرُ الذُّنُوبَ إِلَّا أَنْتَ ، فَاغْفِرْ لِي مَغْفِرَةً مِنْ عِنْدِكَ وَارْحَمْنِي ، إِنَّك أَنْتَ الْغَفُورُ الرَّحِيمُ \n\n رواه البخاري برقم 6326 ، رواه مسلم برقم 2705 \n\n 4/ اللَّهُمَّ أَعِنِّي عَلَى ذِكْرِكَ ، وَشُكْرِكَ ، وَحُسْنِ عِبَادَتِكَ \n\n رواه أحمد برقم 22119 ، رواه أبو داود برقم 1522، رواه النَّسائي برقم 1304، وصححه الألباني صحيح الجامع 2/1320 \n\n5/ اللَّهُمَّ إِنِّي أَعُوذُ بِكَ مِنْ الْبُخْلِ ، وَأَعُوذُ بِكَ مِنْ الْجُبْنِ ، وَأَعُوذُ بِكَ أَنْ أُرَدَّ إِلَى أَرْذَلِ الْعُمُرِ، وَأَعُوذُ بِكَ مِنْ فِتْنَةِ الدُّنْيَا ، وَأَعُوذُ بِكَ مِنْ عَذَابِ الْقَبْرِ \n\n رواه البخاري برقم 6370 \n\n6/ اللَّهُمَّ حَاسِبْنِي حِسَابًا يَسِيرًا \n\n رواه أحمد برقم 24215 وصححه الألباني تحقيق مشكاة المصابيح 3/1544 \n\nثم يُسلِّم ملتفتاً في سلامه ، والتفاته في الصَّلاة سُنَّة ، والمبالغة في الالتفات سُنَّة أيضاً ؛ وذلك لأنَّ النَّبيّ - صلَّى الله عليه وسلَّم - كان يلتفت حتى يرى مَن وراءه بياضَ خدِّه - صلَّى الله عليه وسلَّم - فعَن سعد بن أبي وقاص - رضي الله عنه - قال: كُنْتُ أَرَى رَسُولَ اللّهِ - صَلَّى اللَّهُ عَلَيْهِ وَسَلَّمَ- يُسَلِّمُ عَنْ يَمِينِهِ وَعَنْ يَسَارِهِ ، حَتَّى أَرَى بَيَاضَ خَدِّهِ \n\n رواه مسلم برقم 582 \n\n "},
        {"text": "أذكار بعد الصلاة وعددها (15) أذكار \n\n ستجدها في الصفحة الرئيسية للتطبيق ◀️"}

    ],

    "taam": [
        {"text": "التسمية أول الطعام \n\n عن عمرَ بن أبي سلمةَ - رضي الله عنه - يقولَ:  كُنْتُ غُلَامًا فِي حَجْرِ رَسُولِ اللَّهِ - صَلَّى اللَّهُ عَلَيْهِ وَسَلَّمَ - وَكَانَتْ يَدِي تَطِيشُ فِي الصَّحْفَةِ ، فَقَالَ لِي رَسُولُ اللَّهِ - صَلَّى اللَّهُ عَلَيْهِ وَسَلَّمَ - : يَا غُلَامُ سَمِّ اللَّهَ ،وَكُلْ بِيَمِينِكَ ،وَكُلْ مِمَّا يَلِيكَ فَمَا زَالَتْ تِلْكَ طِعْمَتِي بَعْدُ  رواه البخاري برقم (5376) ، رواه مسلم برقم (2022). وإذا نسي التسمية: فإنه يسن أن يقول إذا تذكرها: بسم الله أوله وآخره .لحديث عائشة - رضي الله عنها - ، أنَّ رسول الله - صلَّى الله عليه وسلَّم - قال:  إذَا أكَلَ أحَدُكُم فَلْيَذْكُرِ اسْمَ الله ، فإنْ نَسِيَ أنْ يَذْكُرَ اسْمَ الله في أوَّلِهِ ، فَلْيَقُلْ : بِسْمِ الله أوَّلَهُ وَآخِرَهُ  رواه أبو داود برقم (3767) ، رواه الترمذي برقم (1858)، وصححه الألباني. وكذلك دلّ الحديث على أن الإنسان يأكل بيمينه حتى لا يشابه الشيطان ، فالمسلم إذا لم يُسمِّ شاركه الشيطان في طعامه ، وإذا أكل أو شرب بشماله شابه الشيطان بذلك ؛ لأن الشيطان يأكل ، ويشرب بشماله . ويدلّ عليه : حديث عبد اللّه بن عُمَرَ- رضي الله عنه - أَن رسول اللّه - صلَّى الله عليه وسلَّم - قَالَ : لاَ يَأْكُلَنَّ أَحَدٌ مِنْكُمْ بِشِمَالِهِ ، وَلاَ يَشْرَبَنَّ بِهَا، فإِنَّ الشَّيْطَانَ يَأْكُلُ بِشِمالِهِ وَيَشْرَبُ بِهَا . قَالَ : وَكَانَ نَافِعٌ يَزِيدُ فِيهَا : وَلاَ يَأْخُذُ بِهَا وَلاَ يَعْطِي بِهَا  رواه مسلم برقم (2020) .والشيطان حريص في أن يدخل البيوت ؛ ليبيت فيها ، و يشارك أهلها الطعام والشراب ، عن جابر بن عبد اللّه – رضي الله عنهما- أنَّه سمع النَّبِيَّ - صلَّى الله عليه وسلَّم - يقول:  إِذَا دَخَلَ الرَّجُلُ بَيْتَهُ ، فَذَكَرَ اللّهَ عِنْدَ دُخُولِهِ وَعِنْدَ طَعَامِهِ ، قَالَ الشَّيْطَانُ: لاَ مَبِيتَ لَكُمْ وَلاَ عَشَاءَ ، وَإِذَا دَخَلَ فَلَمْ يَذْكُرِ اللّهَ عِنْدَ دُخُولِهِ، قَالَ الشَّيْطَانُ: أَدْرَكْتُمُ الْمَبِيتَ. وَإِذَا لَمْ يَذْكُرِ اللّهَ عِنْدَ طَعَامِهِ، قَالَ: أَدْرَكْتُمُ الْمَبِيتَ وَالْعَشَاءَ رواه مسلم برقم (2018) ."},
        {"text": "الأكل مما يلي \n\n لحديث عمر بن أبي سلمة –رضي الله عنه- يقول:  كُنْتُ غُلَامًا فِي حَجْرِ رَسُولِ اللَّهِ - صَلَّى اللَّهُ عَلَيْهِ وَسَلَّمَ - وَكَانَتْ يَدِي تَطِيشُ فِي الصَّحْفَةِ ، فَقَالَ لِي رَسُولُ اللَّهِ - صَلَّى اللَّهُ عَلَيْهِ وَسَلَّمَ - : يَا غُلَامُ سَمِّ اللَّهَ ،وَكُلْ بِيَمِينِكَ ،وَكُلْ مِمَّا يَلِيكَ فَمَا زَالَتْ تِلْكَ طِعْمَتِي بَعْدُ  رواه البخاري برقم (5376) ، رواه مسلم برقم (2022)."},
        {"text": "أخذ اللقمة الساقطة، وإماطة ما بها من أذى، وأكلها \n\n لحديث جَابِرٍ - رضي الله عنه -  قال : سمعت النَّبيَّ - صلَّى الله عليه وسلَّم – يقول :  إِنَّ الشَّيْطَانَ يَحْضُرُ أَحَدَكُمْ عِنْدَ كُلِّ شَيْءٍ مِنْ شَأْنِهِ ، حَتَّى يَحْضُرَهُ عِنْدَ طَعَامِهِ ، فَإِذَا سَقَطَتْ مِنْ أَحَدِكُمُ اللُّقْمَةُ فَلْيُمِطْ مَا كَانَ بِهَا مِنْ أَذَىً ، ثُمَّ لْيَأْكُلْهَا، وَلاَ يَدَعْهَا لِلشَّيْطَانِ، فَإِذَا فَرَغَ فَلْيَلْعَقْ أَصَابِعَهُ ، فَإِنَّهُ لاَ يَدْرِي فِي أَيِّ طَعَامِهِ تَكُونُ الْبَرَكَةُ رواه مسلم برقم (2033).والمتأمل للحديث يجد الشيطان حريصاً على مشاركة الإنسان في كل أموره ؛ لينزع البركة من حياته ، ويفسد عليه كثيرٌ من شأنه ، ومما يدلّ على حرصه على ملازمة العبد في كل أموره قوله - صلَّى الله عليه وسلَّم - :  إِنَّ الشَّيْطَانَ يَحْضُرُ أَحَدَكُمْ عِنْدَ كُلِّ شَيْءٍ مِنْ شَأْنِهِ ."},
        {"text": "لعق الأصابع \n\n ولعقها ، أي : لحسها بطرف لسانه ، فالسُّنَّة أن يلعقها ، أو يُلعِقْها غيره كزوجته مثلاً ، بل السُّنَّة ألَّا يمسح ما يعلق بيده بمنديل ، ونحوه حتى يلعقها.ويدلّ عليه : حديث جابر - رضي الله عنه - السابق .وفي الصحيحين من حديث ابن عبّاس - رضي الله عنهما - أنَّ النَّبيَّ - صلَّى الله عليه وسلَّم - قال:  إِذَا أَكَلَ أَحَدُكُمْ فَلَا يَمْسَحْ يَدَهُ حَتَّى يَلْعَقَهَا، أَوْ يُلْعِقَهَا  رواه البخاري برقم (5456) ، ورواه مسلم برقم (2033)."},
        {"text": "سَلْتُ القَصْعَة \n\n والمقصود مِن سَلْتُ القَصْعَة : تنظيف الآكل حافته من الطعام ، فمثلاً : من يأكل أرزاً ، فإن السُّنَّة ألّا يُبْقِي شيئاً في حافته التي يأكل منها ، فيمسح ما بقي في حافته ، ويأكله ، فقد تكون البركة في هذا المتبقي في حافته.ويدلّ عليه: حديث أنس - رضي الله عنه - قال :  وَأَمَرَنَا - أيّ النَّبيّ - صلَّى الله عليه وسلَّم - أَنْ نَسْلُتَ الْقَصْعَةَ رواه مسلم برقم (2034)، وفي رواية لمسلم من حديث أبي هريرة - رضي الله عنه - :  وَلْيَسْلُتْ أَحَدُكُمُ الصَّحْفَةَ  رواه مسلم برقم (2035) .قال شيخنا ابن عثيمين - رحمه الله -  :  بمعنى : أن تتبع ما علق فيه من طعام بأصابعك ، وتلعقها ، فهذا أيضاً من السُّنَّة التي غفل عنها كثير من الناس مع الأسف حتى من طلبة العلم أيضاً انظر: شرح رياض الصالحين (1/892 ) ."},
        {"text": "الأكل بثلاث أصابع \n\n والسُّنَّة أن يأكل بثلاث أصابع ، وهذا فيما يُحمل بثلاث أصابع كالتمر مثلاً، فيُسن أن يأكله بثلاث أصابع . ويدلّ عليه : حديث كَعْبِ بْنِ مالك - رضي الله عنه – قال :  كَانَ رَسُولُ اللّهِ - صَلَّى اللَّهُ عَلَيْهِ وَسَلَّمَ - يَأْكُلُ بِثَلاَثِ أَصَابِعَ ، وَيَلْعَقُ يَدَهُ قَبْلَ أَنْ يَمْسَحَهَا  رواه مسلم برقم (2032)."},
        {"text": "التنفس خارج الإناء ثلاثاً \n\n مِن السُّنَّة أن يشرب الإناء على ثلاث دفعات ، ويتنفس بعد كل واحدة . ويدلّ عليه : حديث أَنَسٍ - رضي الله عنه - قال: كَانَ رَسُولُ اللّهِ - صلَّى الله عليه وسلَّم - يَتَنَفَّسُ فِي الشَّرَابِ ثَلاَثاً ، وَيَقُولُ : إِنَّهُ أَرْوَى ، وَأَبْرَأُ ، وَأَمْرَأُ، قَالَ أَنَسٌ - رضي الله عنه - :فَأَنَا أَتَنَفَّسُ فِي الشَّرَابِ ثَلاَثاً رواه البخاري برقم (5631) ، رواه مسلم برقم (2028).والمقصود من التنفس في الإناء : التنفس أثناء شربه للإناء ، بمعنى : أنه يتنفس خارج الإناء ؛ لأنَّ التنفس في الإناء مكروه ؛ لحديث أبي قَتادة - رضي الله عنه - في الصحيحين ، قال: قال رسول الله - صلَّى الله عليه وسلَّم - : إِذَا شَرِبَ أَحَدُكُمْ فَلَا يَتَنَفَّسْ فِي الْإِنَاءِ  رواه البخاري برقم (5630) ، رواه مسلم برقم (267)."},
        {"text": "حمد الله - تعالى- بعد الطعام \n\n ويدل على هذه السنة : \n\n حديث أنس بن مالك - رضي الله عنه -  قال: قال رسول اللّه - صلَّى الله عليه وسلَّم - :  إِنَّ اللّه لَيَرْضَى عَنِ الْعَبْدِ أَنْ يَأْكُلَ الأَكْلَةَ فَيَحْمَدَهُ عَلَيْهَا، أَوْ يَشْرَبَ الشَّرْبَةَ فَيَحْمَدَهُ عَلَيْهَا رواه مسلم برقم (2743) .وللحمد صِيَغ متنوعة ، منها :أ.  الْحَمْدُ لِلَّهِ كَثِيرًا طَيِّبًا مُبَارَكًا فِيهِ غَيْرَ مَكْفِيٍّ ، وَلَا مُوَدَّعٍ ، وَلَا مُسْتَغْنًى عَنْهُ رَبَّنَا  رواه البخاري برقم (5458). ب.  الْحَمْدُ لِلَّهِ الَّذِي كَفَانَا وَأَرْوَانَا غَيْرَ مَكْفِيٍّ ، وَلَا مَكْفُورٍ  رواه البخاري برقم (5459). (غيرَ مَكفِيٍّ) : أي: غير محتاج إلى أحد ، فهو الذي يطعم عباده ويكفيهم، ( ولا مُودَّع ) : بفتح الدال ، وتشديدها ، أي : غير متروك ، ( كَفَانَا ) : من الكفاية ، و (أرْوَانَا) من الرِيّ ، (وَلَا مَكْفُورٍ) : أي: مجحود فضله ونعمته ."},
        {"text": "الاجتماع على الطعام \n\n فمن السُّنَّة الاجتماع على الطعام ، وعدم التفرُّق فيه . \n\n ويدلّ عليه: حديث جابر بن عبد اللّه - رضي الله عنهما – يقول : سِمِعْتُ رَسُولَ اللّهِ - صلَّى الله عليه وسلَّم - يَقُولُ:  طَعَامُ الْوَاحِدِ يَكْفِي الإِثْنَيْنِ ، وَطَعَامُ الإِثْنَيْنِ يَكْفِي الأَرْبَعَةَ ، وَطَعَامُ الأَرْبَعَةِ يَكْفِي الثَّمَانِيَةَ رواه مسلم برقم (2059)."},
        {"text": "مدح الطعام إذا أعجبه \n\n مِن السُّنَّة : مدح الطعام إذا أعجبه ، ولا شكّ أنه لا يمدحه إلا بما فيه . ويدل عليه : حديث جابر بن عبد اللّه - رضي الله عنه - أَنَّ النَّبِيَّ - صَلَّى اللَّهُ عَلَيْهِ وَسَلَّمَ - سَأَلَ أَهْلَهُ الأُدُمَ ، فَقَالُوا: مَا عِنْدَنَا إِلاَّ خَلٌّ ، فَدَعَا بِهِ ، فَجَعَلَ يَأْكُلُ بِهِ وَيَقُولُ: نِعْمَ الأُدُمُ الْخَلُّ. نِعْمَ الأُدُمُ الْخَلُّ  رواه مسلم برقم (2052)، والخَلُّ من أنواع الإدام عندهم وهو حلو ليس حامض ، كالخل الذي عندنا اليوم. قال شيخنا ابن عثيمين - رحمه الله - : وهذا أيضاً من هدي النَّبيّ - صلَّى الله عليه وسلَّم - أنه إذا أعجبه الطعام أثنى عليه ، وكذلك مثلاً لو أثنيت على الخبز ، قلت : نعم الخبز خبز بني فلان ، أو ما أشبه ذلك ، فهذا أيضاً سُنَّة الرسول - صلَّى الله عليه وسلَّم -  انظر : شرح رياض الصالحين (2/1057).والمتأمل لواقعنا يجد كثيراً ما يقع الناس في خلاف سُنَّة النَّبيّ - صلَّى الله عليه وسلَّم - فهم لم يكتفوا بترك السُّنَّة بل خالفوها أيضاً ، وذلك بعيبهم للطعام، وذمهم له في بعض الأحيان ، وهذا خلاف هديه - صلَّى الله عليه وسلَّم - ، ففي الصحيحين من حديث أبي هريرةَ - رضي الله عنه - قال: مَا عَابَ النَّبِيُّ - صَلَّى اللَّهُ عَلَيْهِ وَسَلَّمَ - طَعَامًا قَطُّ إِنْ اشْتَهَاهُ أَكَلَهُ وَإِلَّا تَرَكَهُ، رواه البخاري برقم (3563) ، رواه مسلم برقم (2064) ."},
        {"text": "الدعاء لصاحب الطعام \n\nويدلّ عليه : حديث عبد اللّه بن بُسْرٍ - رضي الله عنه – قال : نَزَلَ رَسُولُ اللّهِ - صَلَّى اللَّهُ عَلَيْهِ وَسَلَّمَ - عَلَى أَبِي، قَالَ: فَقَرَّبْنَا إِلَيْهِ طَعَاماً وَوَطْبَةً ، فَأَكَلَ مِنْهَا ، ثُمَّ أُتِيَ بِتَمْرٍ فَكَانَ يَأْكُلُهُ ، وَيُلْقِي النَّوَى بَيْنَ إِصْبَعَيْهِ ، وَيَجْمَعُ السَّبَّابَةَ وَالْوُسْطَى ، ثُمَّ أُتِيَ بِشَرَابٍ فَشَرِبَهُ ، ثُمَّ نَاوَلَهُ الَّذِي عَنْ يَمِينِهِ ، قَالَ فَقَالَ أَبِي، وَأَخَذَ بِلِجَامِ دَابَّتِهِ: ادْعُ اللّهَ لَنَا ، فَقَالَ:  اللَّهُمَّ بَارِكْ لَهُمْ فِي مَا رَزَقْتَهُمْ ، وَاغْفِرْ لَهُمْ ، وَارْحَمْهُمْ رواه مسلم برقم (2042) ، و(الوَطْبَة) : هي الحيس الذي يجمع التمر البرني ، والأقط المدقوق ، والسمن . "},
        {"text": "استحباب أن يسقي الشارب مَن على يمينه قبل يساره \n\nوالمقصود : أنه إذا شرب فمن السُّنَّة أن يعطي مَن على يمينه قبل شماله . \n\n ويدل عليه : حديث أَنَسِ بن مالك - رضي الله عنه - قال: أَتَانَا رَسُولُ اللّهِ - صَلَّى اللَّهُ عَلَيْهِ وَسَلَّمَ - فِي دَارِنَا ، فَاسْتَسْقَى ، فَحَلَبْنَا لَهُ شَاةً ، ثُمَّ شُبْتُهُ مِنْ مَاءِ بِئْرِي هَـذِهِ ، قَالَ: فَأَعْطَيْتُ رَسُولَ اللّهِ - صَلَّى اللَّهُ عَلَيْهِ وَسَلَّمَ -، فَشَرِبَ رَسُولُ اللّهِ ، وَأَبُو بَكْرٍ عَنْ يَسَارِهِ، وَعُمَرُ وِجَاهَهُ ، وَأَعْرَابِيٌّ عَنْ يَمِينِهِ. فَلَمَّا فَرَغَ رَسُولُ اللّهِ مِنْ شُرْبِهِ، قَالَ عُمَرُ: هَـذَا أَبُو بَكْرٍ، يَا رَسُولَ اللّهِ يُرِيهِ إيَّاهُ، فَأَعْطَى رَسُولُ اللّهِ الأَعْرَابِيَّ ، وَتَرَكَ أَبَا بَكْرٍ وَعُمَرَ ، وَقَالَ رَسُولُ اللّهِ - صَلَّى اللَّهُ عَلَيْهِ وَسَلَّمَ -: الأَيْمَنُونَ ، الأَيْمَنُونَ، الأَيْمَنُونَ ، قَالَ أَنَسٌ - رضي الله عنه - :  فَهْيَ سُنَّةٌ، فَهْيَ سُنَّةٌ ، فَهْيَ سُنَّة  رواه البخاري برقم (2571) ، رواه مسلم برقم (2029) . "},
        {"text": "ساقي القوم آخرهم شرباً \n\nيُسنُّ لمن يسقي جماعة أن يكون آخرهم شرباً . \n\n  ويدلّ عليه : حديث أبي قتادة - رضي الله عنه - الطويل ، وفيه: قال:... فَجَعَلَ رَسُولُ اللّهِ - صَلَّى اللَّهُ عَلَيْهِ وَسَلَّمَ - يَصُبُّ وَأَسْقِيهِمْ، حَتَّى مَا بَقِيَ غَيْرِي ، وَغَيْرُ رَسُولِ اللّهِ - صَلَّى اللَّهُ عَلَيْهِ وَسَلَّمَ - ، قَالَ ثُمَّ صَبَّ رَسُولُ اللّهِ - صَلَّى اللَّهُ عَلَيْهِ وَسَلَّمَ - فَقَالَ لِي: اشْرَبْ فَقُلْتُ: لاَ أَشْرَبُ حَتَّى تَشْرَبَ يَا رَسُولَ اللّهِ ، قَالَ:  إِنَّ سَاقِيَ الْقَوْمِ آخِرُهُمْ شُرْباً ، قَالَ: فَشَرِبْتُ وَشَرِبَ رَسُولُ اللّهِ ....  رواه مسلم برقم (681) .فائدة : ومن السُّنَّة لمن شرب لبناً أن يتمضمض بالماء بعد شربه للبن ؛ ليزيل ما في فمه من الدسم الذي يكون من اللبن . ويدلّ عليه : حديث ابْنِ عَبَّاسٍ- رضي الله عنهما -: أَنَّ النَّبِيَّ - صَلَّى اللَّهُ عَلَيْهِ وَسَلَّمَ - شَرِبَ لَبَناً ، فَدَعَا بِمَاءٍ ، فَتَمَضْمَضَ ، وَقَالَ: إِنَّ لَهُ دَسَماً رواه البخاري برقم (211) ، رواه مسلم برقم (358) ."},
        {"text": "تغطية الإناء، وذكر اسم الله - تعالى- عند قدوم الليل \n\n يُسَنُّ تغطية الإناء المكشوف عند قدوم الليل ، وإيكاء السقاء - أي: إغلاقه- إن كان له غلقاً ، وذكر اسم الله عند ذلك . \n\n ويدلّ عليه : حديث جابر بْنِ عبد اللّه - رضي الله عنهما - قَالَ: سَمِعْتُ رَسُولَ اللّهِ - صَلَّى اللَّهُ عَلَيْهِ وَسَلَّمَ - يَقُولُ:  غَطُّوا الإِنَاءَ ، وَأَوْكُوا السِّقَاءَ ، فَإنَّ فِي السَّنَةِ لَيْلَةً يَنْزِلُ فِيهَا وَبَاءٌ ، لاَ يَمُرُّ بِإِنَاءٍ لَيْسَ عَلَيْهِ غِطَاءٌ ، أَوْ سِقَاءٍ لَيْسَ عَلَيْهِ وِكَاءٌ ، إِلاَّ نَزَلَ فِيهِ مِنْ ذلِكَ الْوَبَاءِ رواه مسلم برقم (2014)، وعند البخاري من حديث جابرٍ - رضي الله عنهما - أيضاً:  وَأَوْكُوا قِرَبَكُمْ ، وَاذْكُرُوا اسْمَ اللَّهِ ، وَخَمِّرُوا آنِيَتَكُمْ ، وَاذْكُرُوا اسْمَ اللَّهِ ، وَلَوْ أَنْ تَعْرُضُوا عَلَيْهَا شَيْئًا  رواه البخاري برقم (5623) ."}

    ],

    "salam": [
        {"text": "من السُّنَّة : إلقاء السلام . \n\n  والأدلة على السُّنيَّة كثيرة مستفيضة ، ومنها: حديث أبي هريرة - رضي الله عنه -  أَنَّ رَسُولَ اللّهِ - صلَّى الله عليه وسلَّم - قَالَ:  حَقُّ الْمُسْلِمِ عَلَى الْمُسْلِمِ سِتٌّ ، قِيلَ: مَا هُنَّ يَا رَسُولَ اللّهِ ؟ قَالَ:  إِذَا لَقِيتَهُ فَسَلِّمْ عَلَيْهِ ، وَإِذَا دَعَاكَ فَأَجِبْهُ ، وَإِذَا اسْتَنْصَحَكَ فَانْصَحْ لَهُ ، وَإِذَا عَطَسَ فَحَمِدَ اللّهَ فَشمِّتْهُ، وَإِذَا مَرِضَ فَعُدْهُ، وَإِذَا مَاتَ فَاتَّبِعْهُ  رواه مسلم برقم (2162). - وأمَّا ردُّه فهو : واجب ، ويدل عليه :  قوله تعالى:{وَإِذَا حُيِّيْتُم بِتَحِيَّةٍ فَحَيُّواْ بِأَحْسَنَ مِنْهَا أَوْ رُدُّوهَا إِنَّ اللّهَ كَانَ عَلَى كُلِّ شَيْءٍ حَسِيباً} [النساء : 86].  والأصل في الأمر الوجوب ما لم يصرفه صارف، ونقل الإجماع على وجوب الرد غير واحد من أهل العلم ، منهم : ابن حزم ، وابن عبد البر ، والشيخ تقي الدين وغيرهم - رحم الله الجميع - ، انظر : الآداب الشرعية (1/356) ط . مؤسسة الرسالة. - وأفضل لفظ بالسَّلام ، والردّ ، وأكمله ، هو: ( السلام عليكم ورحمة الله وبركاته ) فإن هذه أحسن تحية وأكملها . قال ابن القيم - رحمه الله - :  وكان هديه - أي : النَّبي صلَّى الله عليه وسلَّم - انتهاء السَّلام ، إلى : ( وبركاته )  انظر : زاد المعاد (2/417 ). وإفشاء السلام ؛ سُنَّة بل سُنَّة مرغَّب بها بفضل عظيم ؛ لحديث أبي هريرة - رضي الله عنه – قال : قال رسول اللّه - صلَّى الله عليه وسلَّم - :  وَالَّذِي نَفْسِي بِيَدِهِ لاَ تَدْخُلُونَ الْجَنَّةَ حَتَّى تُؤْمِنُوا، وَلاَ تُؤْمِنُوا حَتَّى تَحَابُّوا، أَوَلاَ أَدُلُّكُمْ عَلَى شَيْءٍ إِذَا فَعَلْتُمُوهُ تَحَابَبْتُمْ ؟ أَفْشُوا السَّلاَمَ بَينَكُمْ رواه مسلم برقم (54)."},
        {"text": "استحباب تكرار السلام ثلاثًا، إن دعت الحاجة لذلك. \n\n كأن يشك في سماع المُسَلَّم عليه حينما سلَّمَ عليه أول مرَّة ؛ فيستحب أن يُكرِّر مرتين ، وإن لم يسمع ، فثلاثاً ، وكذا إذا دخل على جمع كثير ، كأن يدخل على مجلس كبير، فيه جمع كثير ، فلو سلَّم مرَّة في أول دخوله لم يسمعه إلا من كان أول المجلس ، فيحتاج إلى أن يُسلِّم ثلاثاً ؛ من أجل أن يستوعب جميع مَن في المجلس . ويدلّ عليه : حديث أنس - رضي الله عنه - عنِ النبيِّ - صلَّى الله عليه وسلَّم - : أَنَّهُ كَانَ إِذَا تَكَلَّمَ بِكَلِمَةٍ أَعَادَهَا ثَلَاثًا ؛ حَتَّى تُفْهَمَ عَنْهُ ، وَإِذَا أَتَى عَلَى قَوْمٍ فَسَلَّمَ عَلَيْهِمْ ، سَلَّمَ عَلَيْهِمْ ثَلَاثًا  رواه البخاري برقم (95) . ويؤخذ من حديث أنس - رضي الله عنه - السَّابق ، سنيَّة إعادة الكلمة ثلاثاً إذا دعت الحاجة للتكرار ، كأن يتكلم ولا تفهم عنه الكلمة ، فيُسنُّ أن يكرِّرها ، فإن لم تُفهم كرَّرها الثالثة ."},
        {"text": "من السُّنَّة تعميم السلام على من عرفت، ومن لم تعرف. \n\n لحديث عبد الله بن عَمْرٍو - رضي الله عنهما -  أَنَّ رَجُلاً سَأَلَ رَسُولَ اللّهِ - صلَّى الله عليه وسلَّم - : أَيُّ الإِسْلاَمِ خَيْرٌ؟ قَالَ:  تُطْعِمُ الطَّعَامَ ، وَتَقْرَأُ السَّلاَمَ عَلَى مَنْ عَرَفْتَ ، وَمَنْ لَمْ تَعْرِفْ رواه البخاري برقم (12) ، رواه مسلم برقم (39) ."},
        {"text": "السُّنَّة أن يكون ابتداء السلام ممن جاءت السُّنَّة بابتدائه. \n\nعن أبي هريرة - رضي الله عنه – يقول : قَالَ رَسُولُ اللهِ - صلَّى الله عليه وسلَّم - :  يُسَلِّمُ الرَّاكِبُ عَلَى المَاشِي، والمَاشِي عَلَى القَاعِدِ، وَالقَلِيلُ عَلَى الكَثِيرِ رواه البخاري برقم (6233) ، رواه مسلم برقم (2160)، وفي رواية للبخاري : يُسَلِّمُ الصَّغِيرُ عَلَى الْكَبِيرِ ، وَالْمَارُّ عَلَى الْقَاعِدِ ، وَالْقَلِيلُ عَلَى الْكَثِيرِ  رواه البخاري برقم (6234) .ولا يعني مخالفة الأولى بالسَّلام الكراهة ، بل لا بأس به ، ولكنه خلاف الأولى ، كأن يسلم الكبير على الصغير ، أو الماشي على الرَّاكب ، ونحو ذلك . "},
        {"text": "من السُّنَّة السلام على الصِّبيان. \n\n لحديث أنس بن مالك - رضي الله عنه -: أَنَّهُ كَانَ يَمْشِي مَعَ رَسُولِ اللّهِ - صلَّى الله عليه وسلَّم - فَمَرَّ بِصِبْيَانٍ فَسَلَّمَ عَلَيْهِمْ رواه البخاري برقم (6247) ، رواه مسلم برقم (2168).وفي السَّلام على الصبيان: حملٌ للنَّفس على التواضع ، وتعويد للصبيان على هذه الشعيرة ، وإحياؤها في نفوسهم"},
        {"text": "من السُّنَّة السَّلام عند دخول البيت. \n\n وهذا يدخل في عموم السَّلام ، وذلك بعدما يستاك ؛ لأنَّ السِّواك سُنَّة عند دخول المنزل ، وهذا هو الموضع الرابع من مواضع تأكُّد سنيَّة السواك ، وهو: عند دخول المنزل \n\n لحديث عائشة - رضي الله عنها - عند مسلم قالت : أَنَّ النَّبِيَّ - صلَّى الله عليه وسلَّم - كَانَ إِذَا دَخَلَ بَيْتَهُ بَدَأَ بِالسِّوَاكِ \n\n رواه مسلم برقم 253 \n\nفإذا بدأ بيته بالسِّواك دخل وسلَّم على أهل البيت ، حتى أن بعض أهل العلم قال : من السُّنَّة أن تسلِّم إذا دخلت البيت ، وأي بيت ولو لم يكن فيه أحد ؛ لقوله تعالى: فَإِذَا دَخَلْتُم بُيُوتاً فَسَلِّمُوا عَلَى أَنفُسِكُمْ تَحِيَّةً مِّنْ عِندِ اللَّهِ مُبَارَكَةً طَيِّبَةً كَذَلِكَ يُبَيِّنُ اللَّهُ لَكُمُ الْآيَاتِ لَعَلَّكُمْ تَعْقِلُون \n\n النور:61 \n\nقال ابن حجر - رحمه الله - : ويدخل في عموم إفشاء السَّلام على النفس لمن دخل مكاناً ليس فيه أحد ؛ لقوله تعالى: فَإِذَا دَخَلْتُم بُيُوتاً فَسَلِّمُوا عَلَى أَنفُسِكُمْ... \n\n انظر : فتح الباري ، حديث 6235 ، باب إِفشاءِ السلام \n\nفائدة : تحصَّل مما سبق أنه يُسَنُّ عند دخول المنزل ثلاث سُنَن : \n\nالأولى : ذكر اسم الله - تعالى - لاسيما ليلاً \n\nلحديث جابر بْنِ عبد اللّه - رضي الله عنهما - أَنَّه سمـع النَّبيَّ - صلَّى الله عليه وسلَّم - يقول: إِذَا دَخَلَ الرَّجُلُ بَيْتَهُ، فَذَكَرَ اللّهَ عِنْدَ دُخُولِهِ وَعِنْدَ طَعَامِهِ، قَالَ الشَّيْطَانُ: لاَ مَبِيتَ لَكُمْ وَلاَ عَشَاءَ. وَإِذَا دَخَلَ فَلَمْ يَذْكُرِ اللّهَ عِنْدَ دُخُولِهِ ، قَالَ الشَّيْطَانُ: أَدْرَكْتُمُ الْمَبِيتَ ، وَإِذَا لَمْ يَذْكُرِ اللّهَ عِنْدَ طَعَامِهِ، قَالَ: أَدْرَكْتُمُ الْمَبِيتَ ، وَالْعَشَاءَ \n\n رواه مسلم برقم 2018 \n\nالثانية : السِّواك \n\nلحديث عائشة - رضي الله عنها - عند مسلم: أَنَّ النَّبِيَّ - صلَّى الله عليه وسلَّم - كَانَ إِذَا دَخَلَ بَيْتَهُ بَدَأَ بِالسِّوَاكِ \n\n رواه مسلم برقم 253 \n\nالثالثة : السَّلام على أهل البيت \n\n"},
        {"text": "من السُّنَّة خفض الصوت بالسَّلام، إذا دخل على قوم، وفيهم نائمون. \n\n وهكذا كان يفعل النَّبي - صلَّى الله عليه وسلَّم - ،كما في حديث المقداد بن الأسود- رضي الله عنه - ففيه قال : ... فَكُنَّا نَحْتَلِبُ فَيَشْرَبُ كُلُّ إنْسَانٍ مِنَّا نَصِيبَهُ ، وَنَرْفَعُ لِلنَّبِيِّ - صلَّى الله عليه وسلَّم- نَصِيبَهُ ، قَالَ: فَيَجِيءُ مِنَ اللَّيْلِ فَيُسَلِّمُ تَسْلِيماً لاَ يُوقِظُ نَائِماً، وَيُسْمِـعُ الْيَقْظَانَ  رواه مسلم برقم (2055) ."},
        {"text": "من السُّنَّة تبليغ السَّلام . \n\n فتبليغ السَّلام سُنَّة كأن يقول لك شخص : سلِّم لي على فلان ، فإنَّ من السُّنَّة أن توصِّل هذا السَّلام لصاحبه .ويدلّ عليه : لحديث عائشة - رضي الله عنها - أَنَّ النَّبيَّ - صلَّى الله عليه وسلَّم - قال لها:  إِنَّ جِبْرِيلَ يَقْرَأُ عَلَيْكِ السَّلاَمَ  قَالَتْ: فَقُلْتُ: وَعَلَيْهِ السَّلاَمُ وَرَحْمَةُ اللّهِ رواه البخاري برقم (3217) ، رواه مسلم برقم (2447).ففي الحديث إيصال السَّلام لصاحبه؛ كما أوصل النَّبيُّ - صلَّى الله عليه وسلَّم - سلام جبريل - عليه السلام - على عائشة - رضي الله عنها - ، ويؤخذ من الحديث السَّابق أيضاً سنيَّة بعث السَّلام مع أحد."},
        {"text": "السَّلام عند دخول المجلس، وعند مفارقته أيضاً. \n\nلحديث أبي هريرة - رضي الله عنه - قال : قال رَسولُ الله - صلَّى الله عليه وسلَّم -: إِذَا انْتَهَى أَحَدُكُمْ إِلَى المَجْلِسِ فَلْيُسَلِّمْ، فإِذَا أَرَادَ أَنْ يَقُومَ فَلْيُسَلِّمْ ، فلَيْسَتِ الأولَى بِأَحَقَّ مِنَ الآخِرَةِ  رواه أحمد برقم (9664)، وأبو داود برقم (5208) ، والترمذي برقم (2706)،وصححه الألباني (صحيح الجامع 1/132). "},
        {"text": "تُسَنُّ المصافحة مع السَّلام عند اللُّقيا. \n\nوعلى هذا عمل الصحابة - رضي الله عنهم - ، دلَّ على ذلك : حديث قَتادةَ - رضي الله عنه -  قال:  قُلْتُ لِأَنَسٍ : أَكَانَتْ الْمُصَافَحَةُ فِي أَصْحَابِ النَّبِيِّ - صَلَّى اللَّهُ عَلَيْهِ وَسَلَّمَ - ؟ قَالَ : نَعَمْ  رواه البخاري برقم (6263). "},
        {"text": "يُسَنُّ التبسّم وطلاقة الوجه عند اللقاء. \n\n لحديث أَبِي ذَرّ - رضي الله عنه -  قال : قال لي النَّبيُّ - صلَّى الله عليه وسلَّم - :  لاَ تَحْقِرَنَّ مِنَ الْمَعْرُوفِ شَيْئاً، وَلَوْ أَنْ تَلْقَى أَخَاكَ بِوَجْهٍ طَلْقٍ رواه مسلم برقم (2626)، وعند الترمذي من حديث أبي ذَرّ - رضي الله عنه - قال رسول الله - صلَّى الله عليه وسلَّم - :  تَبَسُّمُكَ في وَجْهِ أَخِيكَ لَكَ صَدَقَةٌ  رواه الترمذي برقم (1956) ، وصححه الألباني (الصحيحة 572) ."},
        {"text": "تُسَنُّ الكلمة الطيبة فهي صدقة. \n\n وسواء كانت عند اللقاء، أو المجالسة، أو في أي حال، فالكلمة الطيبة سُنَّة؛ لأنها صدقة \n\n  ويدلّ عليه: حديث أبي هريرة - رضي الله عنه - قال: قال رسول الله - صلَّى الله عليه وسلَّم -: وَالْكَلِمَةُ الطَّيِّبَةُ صَدَقَةٌ \n\n رواه البخاري برقم 2989، رواه مسلم برقم 1009 \n\n  وكثيراً ما يجري على ألسنة الناس كلامٌ طيبٌ، لو احتسبوه لأُجروا على ذلك كثيراً، وأخذوا من هذه الصدقات بحظ وافر \n\n  قال شيخنا ابن عثيمين - رحمه الله -: كلمة طيبة مثل أن تقول له: كيف أنت؟ كيف حالك؟ كيف إخوانك؟ كيف أهلك؟ وما أشبه ذلك؛ لأن هذه من الكلمات الطيبة التي تدخل السرور على صاحبك، كل كلمة طيبة فهي صدقة لك عند الله، وأجر، وثواب \n\n انظر: شرح رياض الصالحين لشيخنا 2/996 باب: استحباب طيب الكلام، وطلاقة الوجه عند اللقاء \n\n"},
        {"text": "استحباب ذكر الله - تعالى- في المجلس. \n\n والأحاديث في فضائل مجالس الذكر، والحث عليها كثيرة ، ومن ذلك حديث أبي هريرة - رضي الله عنه - قال: قال رسولُ الله - صلَّى الله عليه وسلَّم - : إِنَّ لِلَّهِ مَلَائِكَةً يَطُوفُونَ فِي الطُّرُقِ يَلْتَمِسُونَ أَهْلَ الذِّكْرِ ، فَإِذَا وَجَدُوا قَوْمًا يَذْكُرُونَ اللَّهَ تَنَادَوْا : هَلُمُّوا إِلَى حَاجَتِكُمْ ، قَالَ فَيَحُفُّونَهُمْ بِأَجْنِحَتِهِمْ إِلَى السَّمَاءِ الدُّنْيَا...رواه البخاري برقم (6408) ، رواه مسلم برقم (2689)."},
        {"text": "يُسَنُّ ختم المجلس بـ : ( كفارة المجلس ). \n\n لحديث أَبي هريرة - رضي الله عنه -  قال: قال رسول الله - صلَّى الله عليه وسلَّم - :  مَنْ جَلَس في مَجْلِسٍ فَكثُرَ فيهِ لَغَطُهُ  فَقَالَ قَبْلَ أَنْ يَقُومَ مِنْ مَجْلِسِهِ ذَلِكَ : سُبْحَانَكَ اللّهُمَّ وَبِحَمْدِكَ أَشْهَدُ أن لاَ إلَهَ إلاّ أنْتَ، أَسْتَغْفِرُكَ وَأَتُوبُ إِلَيْكَ إِلاّ غُفِرَ لَهُ مَا كَانَ في مَجْلِسِهِ ذَلِكَ  رواه الترمذي برقم (3433)، وصححه الألباني (صحيح الجامع 2/1065)."}

    ],

    "zeina": [
        {"text": "من السُّنَّة التَّيامن في التَّنعُّل. \n\n من السُّنَّة إذا أراد المسلم أن يلبس نعليه أن يبدأ باليمنى، ومن السُّنَّة إذا أراد أن ينزع نعليه أن يبدأ باليسرى \n\n  ويدلّ عليه: حديث أبي هريرة - رضي الله عنه - أن رسول الله - صلَّى الله عليه وسلَّم - قال: إِذَا انْتَعَلَ أَحَدُكُمْ فَلْيَبْدَأْ بِالْيَمِينِ وَإِذَا نَزَعَ فَلْيَبْدَأْ بِالشِّمَالِ لِيَكُنْ الْيُمْنَى أَوَّلَهُمَا تُنْعَلُ وَآخِرَهُمَا تُنْزَعُ \n\n رواه البخاري برقم 5856 \n\n  وفي لفظ آخر لمسلم: لاَ يَمْشِ أَحَدُكُمْ فِي نَعْلٍ وَاحِدَةٍ، لِيُنْعِلْهُمَا جَمِيعاً، أَوْ لِيَخْلَعْهُمَا جَمِيعاً \n\n رواه مسلم برقم 2097 \n\n  ففي هذين الحديثين، ثلاث سُنَن: \n\n  1. أن يبدأ باليمنى عند لبس النعال \n\n  2. أن يبدأ باليسرى عند نزع النعال \n\n  3. أن يلبس النعلين جميعاً، أو يخلعهما جميعاً، بحيث لا يمشي بنعل واحدة \n\n"},
        {"text": "مِن السُّنَّة لبس البياض من الثياب. \n\n والمقصود أن يلبس من الألوان في ثيابه (الأبيض) فإنه من السُّنَّة ؛ لحديث ابن عبَّاس - رضي الله عنهما -  قال : قال رسول الله - صلَّى الله عليه وسلَّم - :  الْبَسُوا مِنْ ثِيَابِكُم الْبَيَاضَ فإنَّهَا مِنْ خَيْرِ ثِيَابِكم، وَكَفِّنُوا فِيهَا مَوْتَاكُم رواه أحمد برقم (2219) ، وأبو داود برقم (3878) ، والترمذي برقم (994) وصححه الألباني (صحيح الجامع 1/267) .قال شيخنا ابن عثيمين - رحمه الله -: وهو شامل للبس الثياب البيض : القمص ، والأُزر ، والسراويل ، كلها مما ينبغي أن تكون من البياض ، فإنه أفضل ، ولكن لو أنه لبس من لون آخر فلا بأس ، بشرط ألَّا يكون مما يختص لبسه بالنساء انظر : شرح رياض الصالحين ، لشيخنا (2/1087 )."},
        {"text": "من السُّنَّة استعمال الطِّيب. \n\n لحديث أَنَسٍ - رضي الله عنه - قال: قال رسول اللَّه - صلَّى الله عليه وسلَّم -: حُبِّبَ إلَيَّ مِنَ الدُّنْيَا النِّسَاءُ وَالطِّيبُ وَجُعِلَ قُرَّةُ عَيْنِي فِي الصَّلاَةِ \n\n رواه أحمد برقم 12293، والنَّسَائي برقم 3940، وقال الألباني في صحيح النَّسَائي: حسن صحيح \n\n  وأمَّا لفظ: حُبِّبَ إلَيَّ مِنْ دُنْيَاكُمْ ثَلَاثٌ فضعيف \n\n  - وكان يَكرَه - صلَّى الله عليه وسلَّم - أن توجد منه ريح كريهة: فقد جاء عند البخاري في حديث طويل عن عائشة - رضي الله عنها - قالت: وَكَانَ رَسُولُ اللَّهِ - صَلَّى اللَّهُ عَلَيْهِ وَسَلَّمَ - يَشْتَدُّ عَلَيْهِ أَنْ يُوجَدَ مِنْهُ الرِّيحُ \n\n رواه البخاري برقم 6972، أي: الريح غير الطيبة \n\n  يُكْرَه ردُّ الطيب \n\n  لحديث أَنسٍ - رضي الله عنه -: أَنَّ النَّبِيَّ - صَلَّى اللَّهُ عَلَيْهِ وَسَلَّمَ - كَانَ لَا يَرُدُّ الطِّيبَ \n\n رواه البخاري برقم 2582 \n\n"},
        {"text": "من السُّنَّة التيمُّن عند ترجيل الشَّعَر. \n\n والمقصود بترجيل الشعر هو : مشطه ، فإنَّ مِن السُّنَّة أن يبدأ بالجهة اليمنى ، ثم اليسرى. \n\n ويدلّ عليه :حديث عائشة - رضي الله عنها - قالت: كَانَ النَّبيُّ - صلَّى الله عليه وسلَّم - يُعجِبهُ التَّيَمُّنُ في تَنَعُّلهِ وتَرَجُّلهِ وطُهورِه وفي شأنهِ كلِّه رواه البخاري برقم (168) ، رواه مسلم برقم (268) ."}


    ],

    "alaetas": [
        {"text": " يُسَنُّ للعاطس أن يقول :  الحمد لله  .  \n\n لحديث أبي هريرة - رضي الله عنها -  عن النَّبيِّ - صلَّى الله عليه وسلَّم - قال:  إِذَا عَطَسَ أَحَدُكُمْ فَلْيَقُلْ : الْحَمْدُ لِلَّهِ ، وَلْيَقُلْ لَهُ أَخُوهُ أَوْ صَاحِبُهُ : يَرْحَمُكَ اللَّهُ ، فَإِذَا قَالَ لَهُ يَرْحَمُكَ اللَّهُ ، فَلْيَقُلْ يَهْدِيكُمُ اللَّهُ ، وَيُصْلِحُ بَالَكُمْ رواه البخاري برقم (6224) .ويسنُّ له أن ينوِّع فيقول أحياناً : الحمد لله على كل حال  ، فقد جاء في رواية أبي داود : إِذَا عَطَسَ أَحَدُكُم فَلْيَقُلْ : الْحَمدُ لله عَلَى كلِّ حَال  رواه أبو داود برقم (5031) ، وقال ابن القيّم - رحمه الله  في زاد المعاد (2/436 ) عن هذا الحديث: إسناده صحيح .ويقول له المشمِّت : يرحمك الله  ، ويُسَنُّ للعاطس أن يردَّ عليه ، فيقول : يَهْدِيكُمُ اللَّهُ ، وَيُصْلِحُ بَالَكُمْ  وكل هذا دلَّ عليه حديث أبي هريرة - رضي الله عنه - السَّابق ."},
        {"text": "السُّنَّة إذا لم يحمد الله - تعالى- العاطس أنه لا يُشمَّت . \n\n فإذا لم يحمد اللهَ - تعالى - العاطس فليس من السُّنَّة أن نشمِّته، بل السُّنَّة ألا يُشمَّت \n\n  لحديث أنس - رضي الله عنه - قال: عَطَسَ رَجُلَانِ عِنْدَ النَّبِيِّ - صَلَّى اللَّهُ عَلَيْهِ وَسَلَّمَ - فَشَمَّتَ أَحَدَهُمَا، وَلَمْ يُشَمِّتْ الْآخَرَ، فَقَالَ الرَّجُلُ: يَا رَسُولَ اللَّهِ شَمَّتَّ هَذَا وَلَمْ تُشَمِّتْنِي، قَالَ: إِنَّ هَذَا حَمِدَ اللَّهَ وَلَمْ تَحْمَدْ اللَّهَ \n\n رواه البخاري برقم 6225 \n\n  وهذا من فعله - صلَّى الله عليه وسلَّم - وجاء من قوله - صلَّى الله عليه وسلَّم - ما رواه مسلم، عن أبي موسى - رضي الله عنه - قال: سَمِعْتُ رَسُولَ اللّهِ - صَلَّى اللَّهُ عَلَيْهِ وَسَلَّمَ - يقول: إِذَا عَطَسَ أَحَدُكُمْ فَحَمِدَ اللّهَ، فَشَمِّتُوهُ، فَإِنَّ لَمْ يَحْمَدِ اللّهَ، فَلاَ تُشَمِّتُوهُ \n\n رواه مسلم برقم 2992 \n\n  ولكن إذا كان المقام مقام تعليم كأن يربي الأبُ ابنَه، أو المعلمُ طلابَه، أو نحو ذلك ممّا هو في مقام التعليم، فإنه يقول له: قل الحمد لله؛ ليربيه على هذه السُّنَّة فقد يكون جاهلاً في سنّيتها \n\n  وكذا من كان مزكوماً فإنه لا يُشمَّت بعد الثالثة، فإذا عطس ثلاث مرات يُشمَّت، وبعدها لا يُشمَّت \n\n  ويدلّ عليه: ما رواه أبو داود في سننه عن أبي هريرة - رضي الله عنه - موقوفاً ومرفوعاً، قالَ: شَمِّتْ أَخاكَ ثَلاَثاً فَمَا زَادَ فَهُوَ زُكَامٌ \n\n رواه أبو داود برقم 5034، وقال الألباني - رحمه الله -: حسن موقوف، ومرفوع (صحيح أبي داود 4/308) \n\n  ويؤيده ما رواه مسلم في صحيحه، من حديث سَلَمَةَ بْنِ الأَكْوَعِ - رضي الله عنه - أَنَّهُ سَمِعَ النَّبِيَّ - صَلَّى اللَّهُ عَلَيْهِ وَسَلَّمَ - وَعَطَسَ رَجُلٌ عِنْدَهُ فَقَالَ لَهُ: يَرْحَمُكَ اللّهُ، ثُمَّ عَطَسَ أُخْرَى فَقَالَ لَهُ رَسُولُ اللّهِ - صلَّى الله عليه وسلَّم -: الرَّجُلُ مَزْكُومٌ \n\n رواه مسلم برقم 2993 \n\n  فتحصَّل مما سبق أنَّ العاطس لا يُشمَّت في حالين: \n\n  1. إذا لم يحمد الله - تعالى - \n\n  2. إذا زاد على ثلاث مرات؛ لأنَّه مزكوم \n\n"}

    ],

    "tsawob": [
        {"text": "من السُّنَّة كظم الفم عند التثاؤب، أو ردُّه باليد. \n\nويدلّ عليه :حديث أبي هريرة - رضي الله عنه - عن النَّبيِّ - صلَّى الله عليه وسلَّم - قال:  إِنَّ اللَّهَ يُحِبُّ الْعُطَاسَ ، وَيَكْرَهُ التَّثَاؤُبَ ، فَإِذَا عَطَسَ فَحَمِدَ اللَّهَ ، فَحَقٌّ عَلَى كُلِّ مُسْلِمٍ سَمِعَهُ أَنْ يُشَمِّتَهُ ، وَأَمَّا التَّثَاؤُبُ فَإِنَّمَا هُوَ مِنْ الشَّيْطَانِ فَلْيَرُدَّهُ مَا اسْتَطَاعَ ، فَإِذَا قَالَ هَا ضَحِكَ مِنْهُ الشَّيْطَانُ  رواه البخاري برقم (2663) .وعند مسلم من حديث أبي سعيد - رضي الله عنه – ، قال النَّبيُّ - صلَّى الله عليه وسلَّم - :  إِذَا تَثَاوَبَ أَحَدُكُمْ، فَلْيُمْسِكْ بِيَدِهِ عَلَى فِيهِ ، فَإِنَّ الشَّيْطَانَ يَدْخُلُ رواه مسلم برقم (2995)، فيكون كظم التثاؤب إمَّا بالتحكم عن طريق الفم ، وذلك بمنع انفتاحه ، أو بضغط الأسنان على الشفة ، وإمَّا بوضع اليد على الفم ، ونحو ذلك. "},
        {"text": "الأفضل للمتثائب ألَّا يرفع صوته بالتثاؤب \n\n الأفضل للمتثائب ألَّا يرفع صوته بالتثاؤب، كأن يقول: (ها)، أو (آه)، ونحوها من الأصوات التي يصدرها؛ لأنَّ هذا مدعاة لضحك الشيطان عليه \n\n  ويدل عليه: \n\n  حديث أبي هريرة - رضي الله عنه - عن النبيِّ - صلَّى الله عليه وسلَّم - قال: التَّثَاؤُبُ مِنْ الشَّيْطَانِ، فَإِذَا تَثَاءَبَ أَحَدُكُمْ فَلْيَرُدَّهُ مَا اسْتَطَاعَ؛ فَإِنَّ أَحَدَكُمْ إِذَا قَالَهَا ضَحِكَ الشَّيْطَانُ \n\n  رواه البخاري برقم 3298، رواه مسلم برقم 2994 \n\n  وجاء بلفظ عند أحمد - رحمه الله -: إذَا تَثَاءَبَ أَحَدُكُمْ فَلْيَرُدَّه مَا اسْتَطَاع، وَلا يَقُل: آه آه، فَإِنَّ أَحَدَكُم إِذَا فَتَحَ فَاهُ، فَإِنَّ الشَيْطَانَ يَضْحَكُ مِنْهُ أَو بِه \n\n  رواه أحمد برقم 9530، وصححه الألباني (الصحيحة 2420) \n\n  فينبغي للمسلم عند التثاؤب أن: \n\n  1. يكتم التثاؤب ما استطاع \n\n  2. يضع يده على فمه \n\n  3. يتجنب إصدار الأصوات المزعجة \n\n  4. يحاول مقاومة التثاؤب بقدر الإمكان \n\n  لأن في ذلك: \n\n  - اتباعاً لهدي النبي صلى الله عليه وسلم \n\n  - وقاية من استهزاء الشيطان \n\n  - أدباً في التعامل مع الآخرين \n\n  - حفظاً للوقار والهيئة الحسنة \n\n"},
        {"text": "تنبيه \n\n تنبيه : اعتاد بعض الناس على التَّعوذ من الشيطان بعد التثاؤب ، ولا دليل على ذلك بل هو مخالفة لهدي النَّبي - صلَّى الله عليه وسلَّم - ؛ لأنه جاء بذكر لم يقله النَّبيُّ - صلَّى الله عليه وسلَّم - في هذا الموطن ."}

    ],

    "yawmieya": [
        {"text": "قول الذكر الوارد عند دخول الخلاء، والخروج منه. \n\n فيُسَنُّ لمن دخل الخلاء ، أن يقول ما جاء في الصحيحين :قال عن أَنَس - رضي الله عنه - : كَانَ رَسُولُ اللّهِ - صلَّى الله عليه وسلَّم - إِذَا دَخَلَ الْخَلاَءَ، قَالَ:  اللَّهُمَّ إِنِّي أَعُوذُ بِكَ مِنَ الْخُبثِ وَالْخَبَائِثِ رواه البخاري برقم (6322) ، رواه مسلم برقم (375) .( الخبُث ) بضم الباء :ذكران الشياطين ، والخبائث إناثهم ، فتكون الاستعاذة من ذكران الشياطين وإناثهم .و( الخبْث ) بتسكين الباء : الشر ، والخبائث النفوس الشريرة ، فتكون الاستعاذة من الشَّر وأهله، والتسكين أعمّ. وهو أكثر روايات الشيوخ ،كما قال القاضي عياض ، والخطابي وغيرهما - رحم الله الجميع - .- ويُسَنُّ لمن خرج من الخلاء أن يقول :ما جاء في مسند أحمد ، وسنن أبي داود ، والترمذي ، وصححه الألباني: عن عائشة - رضي الله عنها -  قالت:  كَانَ النَّبِيُّ - صلَّى الله عليه وسلَّم - إِذَا خَرَجَ مِنَ الْخَلاَءِ قَالَ: غُفْرَانَكَ رواه أحمد برقم (25220) ، وأبوداود برقم (30) ، والترمذي برقم (7) وصححه الألباني (تحقيق مشكاة المصابيح 1/116) .فائدة : قيل : مناسبة قول :  غفرانك  أنَّ الإنسان لمَّا تخفَّف من أذيَّة الجسم ، تذكَّر أذيَّة الإثم ، فدعا الله- تعالى-  أن يخفف عنه أذيَّة الإثم ، كما منَّ عليه بتخفيف أذية الجسم . ذكره ابن القيم - رحمه الله - انظر : إغاثة اللهفان (1/58 ) .وقيل : إنَّ مناسبة ذلك هو: استغفاره ؛ لانقطاعه عن الذِّكر حال الخلاء ، وقيل غير ذلك."},
        {"text": "تسنُّ كتابة الوصيَّة . \n\n فالوصيَّة سُنَّة لكل مسلم حال المرض ، أو الصِّحة ؛ لقول رسول اللّه - صلَّى الله عليه وسلَّم - :  مَا حَقُّ امْرِىءٍ مُسْلِمٍ ، لَهُ شَيْءٌ يُرِيدُ أَنْ يُوصِيَ فِيهِ ، يَبِيتُ لَيْلَتَيْنِ ، إلاَّ وَوَصِيَّتهُ مَكْتُوبَةٌ عِنْدَهُ رواه البخاري برقم (2783) ، رواه مسلم برقم (1626) من حديث ابن عمر - رضي الله عنهما- ، وذكر الليلتين في الحديث ليس تحديداً ، وإنما المراد به ألَّا يمر عليه زمن قصير إلا ووصيته مكتوبة عنده؛ لأنه لا يدري متى يموت ، وهذه سُنَّة عامَّة لكل الناس .أمَّا الوصية فيما عليه من حقوق الله - تعالى - كزكاة ، أو حج ، أو كفَّارة ، أو حقوق الآدميين كالدَّيْن ، وأداء الأمانات ، فهذه واجبة لا سُنَّة ؛ لأنه يتعلَّق بها أداء حقوق واجبة ، لاسيما إذا لم يعلم بهذه الحقوق أحد ، [ ومالا يتم الواجب إلا به فهو واجب ] ."},
        {"text": "السماحة واللين في البيع والشراء. \n\n وذلك بأن يتحلَّى كل من البائع ، والمشتري ، بالسماحة ، واللين أثناء البيع ، ولا يتشدَّد كل منهما مع الآخر في المساومة في السِّعر والجدل فيه،  بل يتسامحان.ويدلّ عليه :حديث جابرِ بنِ عبدِ الله - رضي الله عنهما -  أنَّ رسول الله - صلَّى الله عليه وسلَّم - قال:  رَحِمَ اللَّهُ رَجُلًا سَمْحًا ؛ إِذَا بَاعَ ، وَإِذَا اشْتَرَى ، وَإِذَا اقْتَضَى  رواه البخاري برقم (2076) .وكذلك إذا طالب بقضاء حَقِّه ، فإنَّ من السُّنَّة أن يُطالب بسهولة ، ولين ؛ لقول النَّبي- صلَّى الله عليه وسلَّم -:  وإذا اقتضى  ."},
        {"text": "صلاة ركعتين بعد كل وضوء. \n\n وهذه من السُّنَن اليوميَّة التي يترتب عليها فضل عظيم ، وهو : دخول الجنة ، فعَن أبي هريرة - رضي الله عنه - : أَنَّ النَّبِيَّ - صَلَّى اللَّهُ عَلَيْهِ وَسَلَّمَ - قَالَ لِبِلَالٍ عِنْدَ صَلَاةِ الْفَجْرِ: يَا بِلَالُ حَدِّثْنِي بِأَرْجَى عَمَلٍ عَمِلْتَهُ فِي الْإِسْلَامِ ؛ فَإِنِّي سَمِعْتُ دَفَّ نَعْلَيْكَ بَيْنَ يَدَيَّ فِي الْجَنَّةِ ، قَالَ: مَا عَمِلْتُ عَمَلًا أَرْجَى عِنْدِي أَنِّي لَمْ أَتَطَهَّرْ طَهُورًا فِي سَاعَةِ لَيْلٍ ، أَوْ نَهَارٍ ، إِلَّا صَلَّيْتُ بِذَلِكَ الطُّهُورِ مَا كُتِبَ لِي أَنْ أُصَلِّيَ رواه البخاري برقم (1149) ، رواه مسلم برقم (2458)، و(دَفَّ نَعْلَيْكَ) يعني : تحريك نعليك ."},
        {"text": "انتظار الصَّلاة . \n\n وانتظار الصلاة من السُّنَن التي يترتَّب عليها فضل عظيم \n\nويدل عليه: \n\nحديث أبي هريرة - رضي الله عنه - أَنَّ رسول اللّه - صلَّى الله عليه وسلَّم - قال: لاَ يَزَالُ أَحَدكُمْ فِي صَلاَةٍ مَا دَامَتِ الصَّلاَةُ تَحْبِسُهُ، لاَ يَمْنَعُهُ أَنْ يَنْقَلِبَ إِلَى أَهْلِهِ إِلاَّ الصَّلاَةُ \n\nرواه البخاري برقم 659، رواه مسلم برقم 649 \n\nوعن أبي هريرة - رضي الله عنه - أَن رسول الله - صلَّى الله عليه وسلَّم - قال: الْمَلَائِكَةُ تُصَلِّي عَلَى أَحَدِكُمْ مَا دَامَ فِي مُصَلَّاهُ، مَا لَمْ يُحْدِثْ، اللَّهُمَّ اغْفِرْ لَهُ، اللَّهُمَّ ارْحَمْهُ، لَا يَزَالُ أَحَدُكُمْ فِي صَلَاةٍ مَا دَامَتْ الصَّلَاةُ تَحْبِسُهُ، لَا يَمْنَعُهُ أَنْ يَنْقَلِبَ إِلَى أَهْلِهِ إِلَّا الصَّلَاةُ \n\nرواه البخاري برقم 659، رواه مسلم برقم 649 \n\nوقوله: ما لم يُحدِثْ أي ما لم يأتِ بشيء ينقض الوضوء، وجاء عند مسلم: \n\nمَا لَمْ يُؤْذِ فِيهِ، مَا لَمْ يُحْدِثْ فِيهِ \n\nرواه مسلم برقم 649 \n\nففي هذا الحديث فوائد عظيمة: \n\n1. أن المُنتظر للصلاة في المسجد في صلاة ما دام ينتظرها \n\n2. أن الملائكة تستغفر له وتدعو له بالرحمة والمغفرة \n\n3. اشتراط بقاء الأجر بعدم الحدث والأذى \n\n4. فضل المكث في المسجد وانتظار الصلوات \n\nوينبغي للمسلم أن: \n\n- يحافظ على وضوئه \n\n- يجتنب إيذاء الآخرين \n\n- يشتغل بالذكر وقراءة القرآن \n\n- يستحضر نية الاعتكاف إن أطال الجلوس \n\n"},
        {"text": "السِّواك . \n\n والسِّواك من السُّنَن المطلقة التي تُفعل في كل وقت ، وكان النَّبيّ - صلَّى الله عليه وسلَّم - يحث عليه كثيراً حتى قال :  أَكْثَرْتُ عَلَيْكُمْ فِي السِّوَاكِ  رواه البخاري برقم (888) من حديث أنس - رضي الله عنه -  ، وقال النَّبيُّ - صلَّى الله عليه وسلَّم - فيه : السِّوَاكُ مَطْهَرَةٌ لِلْفَمِ مَرْضَاةٌ لِلرَّبِّ رواه أحمد برقم (7) ، رواه النَّسَائي برقم (5) من حديث عائشة - رضي الله عنها – وصححه الألباني (الإرواء 1/105) .وتتأكد سنيَّة السواك في مواضع تقدَّم ذكر بعضها لاسيما التي تتكرر في اليوم والليلة ، كالقيام من الليل ، وعند الوضوء ، وعند كل صلاة ، وعند دخول المنزل - والله أعلم - ."},
        {"text": "تجديد الوضوء لكل صلاة \n\n يُسَنُّ للمسلم أن يُجَدد الوضوء لكل صلاة ، فلو أنه توضأ لصلاة المغرب مثلاً ثم صلَّى المغرب ، فإذا جاءت صلاة العشاء يُسنُّ له أن يتوضأ ، ولو كان على طهارة ، فالسُّنَّة أن يتوضأ لكل صلاة وضوءً جديداً .ويدلّ عليه :حديث عند البخاري قال:  كَانَ النَّبِيُّ - صَلَّى اللَّهُ عَلَيْهِ وَسَلَّمَ - يَتَوَضَّأُ عِنْدَ كُلِّ صَلَاةٍ  رواه البخاري (214) .وأيضاً من السُّنَّة أن يكون الإنسان على طهارة خلال يومه ؛ لحديث ثوبان - رضي الله عنه - أنَّ النَّبيُّ - صلَّى الله عليه وسلَّم- قال :  وَلاَ يُحَافِظُ عَلَى الْوُضُوءِ إِلاَّ مُؤْمِنٌ  رواه أحمد برقم (22434) ، رواه ابن ماجه برقم (277) ، رواه الدارمي برقم (655)، وصححه الألباني (صحيح الجامع 1/225) ."}

    ],

    "duaa": [
        {"text": "أن يدعو وهو على طهارة . \n\n لحديث أبي موسى - رضي الله عنه - في الصحيحين ، وقصته مع عَمِّه أبي عامر - رضي الله عنه - ، حين بعثه النَّبيُّ - صلَّى الله عليه وسلَّم - على جيش أوطاس ، وفي الحديث : قُتل أبو عامر - رضي الله عنه - ، وأوصى أبا موسى - رضي الله عنه - أن يُقرئ النَّبيَّ - صلَّى الله عليه وسلَّم - السلام ، ويدعو له ، قال أبو موسى :  فَأَخْبَرْتُهُ بِخَبَرنا وَخَبَر أَبِي عَامِرٍ، وَقُلْتُ لَهُ: قَالَ: قُلْ لَهُ: يَسْتَغْفِرْ لِي ، فَدَعَا رَسُولُ اللّهِ بِمَاءٍ ، فَتَوَضَّأ مِنْهُ ، ثُمَّ رَفَعَ يَدَيْهِ ، ثُمَّ قَالَ:  الّلهُمَّ اغْفِرْ لِعُبَيْدٍ، أَبِي عَامِرٍ ، حَتَّى رَأَيْتُ بَيَاضَ إِبْطَيْهِ ، ثُمَّ قَالَ:  اللّهُمَّ اجْعَلْهُ يَوْمَ الْقِيَامَةِ فَوْقَ كَثِيرٍ مِنْ خَلْقِكَ ، أَوْ مِنَ النَّاسِ رواه البخاري برقم (4323) ، رواه مسلم برقم (2498) ."},
        {"text": "استقبال القِبلة. \n\n وعن عبد اللّه بن عَبَّاس - رضي الله عنهما - قال:  حَدَّثنِي عُمَرُ بْنُ الْخَطَّابِ - رضي الله عنه - قَالَ: لَمَّا كَانَ يَوْمُ بَدْرٍ، نَظَرَ رَسُولُ اللّهِ - صلَّى الله عليه وسلَّم - إلَى الْمُشْرِكِينَ وَهُمْ أَلْفٌ ، وَأَصْحَابُهُ ثَلاَثُمِائَةٍ وَتِسْعَةَ عَشَرَ رَجُلاً ، فَاسْتَقْبَلَ نَبِيُّ اللّهِ الْقِبْلَةَ ، ثُمَّ مَدَّ يَدَيْهِ فَجَعَلَ يَهْتِفُ بِرَبِّهِ: اللَّهُمَّ أَنْجِزْ لِي مَا وَعَدْتَنِي، اللَّهُمَّ آتِ مَا وَعَدْتَنِي، اللَّهُمَّ إنْ تَهْلِكْ هَـذِهِ الْعِصَابَةُ مِنْ أَهْلِ الإِسْلاَمِ لاَ تُعْبَدْ فِي الأَرْضِ فَمَا زَالَ يَهْتِفُ بِرَبِّهِ، مَادّاً يَدَيْهِ ، مُسْتَقْبِلَ الْقِبْلَةِ ، حَتَّى سَقَطَ رِدَاؤُهُ عَنْ مَنْكِبَيْهِ ، فَأَتَاهُ أَبُو بَكْرٍ، فَأَخَذَ رِدَاءَهُ فَأَلْقَاهُ عَلَى مَنْكِبَيْهِ. ثُمَّ الْتَزَمَهُ مِنْ وَرَائِهِ. وَقَالَ: يَا نَبِيَّ اللّهِ كَفَاكَ مُنَاشَدَتَكَ رَبَّكَ ، فَإنَّهُ سَيُنْجِزُ لَكَ مَا وَعَدَكَ... رواه مسلم برقم (1763)."},
        {"text": "رفع اليدين. \n\n ويدلّ عليه حديث ابن عباس - رضي الله عنهما - قال:  حَدَّثنِي عُمَرُ بْنُ الْخَطَّابِ - رضي الله عنه - قَالَ: لَمَّا كَانَ يَوْمُ بَدْرٍ، نَظَرَ رَسُولُ اللّهِ - صلَّى الله عليه وسلَّم - إلَى الْمُشْرِكِينَ وَهُمْ أَلْفٌ ، وَأَصْحَابُهُ ثَلاَثُمِائَةٍ وَتِسْعَةَ عَشَرَ رَجُلاً ، فَاسْتَقْبَلَ نَبِيُّ اللّهِ الْقِبْلَةَ ، ثُمَّ مَدَّ يَدَيْهِ فَجَعَلَ يَهْتِفُ بِرَبِّهِ:  اللَّهُمَّ أَنْجِزْ لِي مَا وَعَدْتَنِي، اللَّهُمَّ آتِ مَا وَعَدْتَنِي، اللَّهُمَّ إنْ تَهْلِكْ هَـذِهِ الْعِصَابَةُ مِنْ أَهْلِ الإِسْلاَمِ لاَ تُعْبَدْ فِي الأَرْضِ فَمَا زَالَ يَهْتِفُ بِرَبِّهِ، مَادّاً يَدَيْهِ ، مُسْتَقْبِلَ الْقِبْلَةِ ، حَتَّى سَقَطَ رِدَاؤُهُ عَنْ مَنْكِبَيْهِ ، فَأَتَاهُ أَبُو بَكْرٍ، فَأَخَذَ رِدَاءَهُ فَأَلْقَاهُ عَلَى مَنْكِبَيْهِ. ثُمَّ الْتَزَمَهُ مِنْ وَرَائِهِ. وَقَالَ: يَا نَبِيَّ اللّهِ كَفَاكَ مُنَاشَدَتَكَ رَبَّكَ ، فَإنَّهُ سَيُنْجِزُ لَكَ مَا وَعَدَكَ... رواه مسلم برقم (1763).والأحاديث لهذه السُّنَّة كثيرة ."},
        {"text": "البدء بالثناء على الله - عز وجل -، والصلاة على رسوله - صلَّى الله عليه وسلَّم -. \n\n لِمَا رواه الترمذي ، عن فَضَالَةَ بن عُبَيْد  - رضي الله عنه - قال : بَيْنَا رَسُولُ اللَّهِ - صَلَّى اللَّهُ عَلَيْهِ وَسَلَّمَ -  قَاعِدٌ إِذْ دَخَلَ رَجُلٌ فَصَلَّى فَقَالَ :  اللَّهُمَّ اغْفِرْ لِي وَارْحَمْنِي ، فَقَالَ رَسُولُ اللَّهِ - صَلَّى اللَّهُ عَلَيْهِ وَسَلَّمَ -: عَجِلْتَ أَيُّهَا الْمُصَلِّي ، إِذَا صَلَّيْتَ فَقَعَدْتَ فَاحْمَدْ اللَّهَ بِمَا هُوَ أَهْلُهُ ، وَصَلِّ عَلَيَّ ، ثُمَّ ادْعُهُ  رواه الترمذي برقم (3476)، وصححه الألباني (صحيح الجامع 1/172)."},
        {"text": "دعاء الله - تعالى - بأسمائه الحسنى. \n\n فيختار من أسماء الله الحسنى ما يلائم دعوته ويوافقها ؛ فإذا سأل الله - سبحانه -  الرزق ، قال: يا رزاق  ، وإذا سأل الله - تعالى -  الرحمة ، قال: يا رحمان يا رحيم، وإذا سأل الله - عز وجلّ  - العِزَّة ، قال: يا عزيز ، وإذا سأل الله - عز وجلّ - المغفرة ، قال   يا غفور  ، وإذا سأله شفاء قال : يا شافي .وهكذا يدعو بما يناسب دعوته ؛ لقوله تعالى :{وَلِلّهِ الأَسْمَاء الْحُسْنَى فَادْعُوهُ بِهَا}[الأعراف:180]."},
        {"text": "تكرار الدعاء، والإلحاح فيه. \n\nويدلّ عليه حديث ابن عباس - رضي الله عنهما - الذي تقدَّم حيث قال النَّبيُّ - صلَّى الله عليه وسلَّم -: اللَّهُمَّ أَنْجِزْ لِي مَا وَعَدْتَنِي، اللَّهُمَّ آتِ مَا وَعَدْتَنِي \n\n  وما زال يهتف بربه - تعالى - حتى سقط رداؤه عن منكبيه، وأبو بكر يلتزمه ويقول له: يَا نَبِيَّ اللّهِ كَفَاكَ مُنَاشَدَتَكَ رَبَّكَ \n\n  رواه مسلم برقم 1763 \n\n  وكذلك ما جاء في الصحيحين، من حديث أبي هريرة - رضي الله عنه - حينما دعا النَّبيُّ - صلَّى الله عليه وسلَّم - لدَوْس، فقال: اللهم اهْدِ دَوْساً وائْتِ بهم، اللهم اهْدِ دَوْساً وائت بهم \n\n  رواه البخاري برقم 2937، رواه مسلم برقم 2524 \n\n  وكذلك ما جاء في صحيح مسلم، في: الرَّجُلُ يُطِيلُ السَّفَرَ، أَشْعَثَ أَغْبَرَ، يَمُدُّ يَدَيْهِ إِلَى السَّمَاءِ. يَا رَبِّ يَا رَبِّ \n\n  رواه مسلم برقم 1015 وهذا تكرار فيه إلحاح \n\n  والسُّنَّة أن يدعو ثلاثاً \n\n  لحديث ابن مسعود - رضي الله عنه - في الصحيحين، وفيه: وَكَانَ إِذَا دَعَا، دَعَا ثَلاثًا، وَإِذَا سأَلَ، سَأَلَ ثَلاثًا، ثُمَّ قَالَ: اللَّهُمَّ عَلَيْكَ بِقُرَيْشٍ ثَلاثَ مَرَّاتٍ \n\n  رواه البخاري برقم 240، رواه مسلم برقم 1794 \n\n  ففي هذه الأحاديث فوائد عظيمة: \n\n  1. مشروعية الإلحاح في الدعاء \n\n  2. تكرار الدعاء ثلاث مرات \n\n  3. رفع اليدين حال الدعاء \n\n  4. الاجتهاد في الدعاء حتى يظهر أثر ذلك على الداعي \n\n  5. الدعاء للأمم بالهداية \n\n  وينبغي للمسلم أن: \n\n  - يلح في دعائه \n\n  - يكرر دعاءه ثلاثاً \n\n  - يرفع يديه حال الدعاء \n\n  - يظهر الخشوع والتضرع \n\n  - لا يستبطئ الإجابة \n\n "},
        {"text": "إخفاء الدعاء. \n\n لقوله تعالى :{ادْعُواْ رَبَّكُمْ تَضَرُّعاً وَخُفْيَةً}[الأعراف:55]، وإخفاء الدعاء أقرب للإخلاص ، ولذا امتدح الله – عز وجلّ -  زكريا - عليه السلام - فقال :{إِذْ نَادَى رَبَّهُ نِدَاء خَفِيّاً }[ مريم:3 ] ؛ طلباً للإخلاص على أحد أقوال أئمة التفسير ."},
        {"text": "ماذا أقول في دعائي ؟ \n\n فائدة : ربما يسأل البعض : ماذا أقول في دعائي ؟  \n\n فالجواب : ادع بما تريده من أمور الدنيا والآخرة ، واحرص في دعائك على جوامع الكَلِم ، وهي الأدعية الواردة في الكتاب والسُّنَّة ، ففيها سؤال خيري الدنيا والآخرة ، وتأمل هذا السؤال حين عُرض على النَّبيِّ - صلَّى الله عليه وسلَّم - فأجاب بكلمات عظيمات ، تجمع للمسلم الدنيا والآخرة ، فما أعظمها من بشارة ، وما أجزلها من عطيَّة ، فتمسك بهن وتدبرهن .عن أبي مالك الأشجعي عن أبيه - رضي الله عنهما- :  أَنَّهُ سَمِـعَ النَّبِي - صلَّى الله عليه وسلَّم - وَأَتَاهُ رَجُلٌ فَقَالَ: يَا رَسُولَ اللّهِ كَيْفَ أَقُولُ حِينَ أَسْأَلُ رَبِّي؟ قَالَ : قُلِ: اللَّهُمَّ اغْفِرْ لِي ، وَارْحَمْنِي ، وَعَافِنِي ، وَارْزُقْنِي ، وَيَجْمَعُ أَصَابِعَهُ إِلاَّ الإِبْهَامَ  فَإِنَّ هؤُلاَءِ تَجْمَعُ لَكَ دُنْيَاكَ وَآخِرَتَكَ رواه مسلم برقم (2697) .وفي رواية له : كَانَ الرَّجُلُ إِذَا أَسْلَمَ عَلَّمَهُ النَّبِيُّ - صلَّى الله عليه وسلَّم -  الصَّلاَةَ ، ثُمَّ أَمَرَهُ أَنْ يَدْعُوَ بِهؤُلاَءِ الْكَلِمَاتِ:  اللَّهُمَّ اغْفِرْ لِي وَارْحَمْنِي ، وَاهْدِنِي ، وَعَافِنِي ، وَارْزُقْنِي رواه مسلم برقم (2697) ."},
        {"text": "يُسَنُّ للإنسان أن يدعو لأخيه بظهر الغيب \n\n فائدة أخرى : يُسَنُّ للإنسان أن يدعو لأخيه بظهر الغيب ، فهي دعوة مستجابة بإذن الله - تعالى -  ، وللداعي فضل عظيم ، وهو ما رواه مسلم في صحيحه ، عن أبي الدرداء - رضي الله عنه - قال : قال رسول الله - صلَّى الله عليه وسلَّم -: دَعْوَةُ الْمَرْءِ الْمُسْلِمِ لأَخِيهِ بِظَهْرِ الْغَيْبِ ، مُسْتَجَابَةٌ ، عِنْدَ رَأْسِهِ مَلَكٌ مُوَكَّلٌ ، كُلَّمَا دَعَا لأَخِيهِ بِخَيْرٍ، قَالَ الْمَلَكُ الْمُوَكَّلُ بِهِ: آمِينَ، وَلَكَ بِمِثْلٍ رواه مسلم برقم (2733)."}


    ],

    "ziekr_allh": [
        {"text": "أعظمه : تلاوة كتاب الله - تعالى- \n\nمن السنن اليومية ذكر الله تعالى.وأعظمه : تلاوة كتاب الله - تعالى-  ، فالتعبد بتلاوته أسهر عيون السلف ، وأقض مضاجعهم {كَانُوا قَلِيلاً مِّنَ اللَّيْلِ مَا يَهْجَعُونَ * وَبِالْأَسْحَارِ هُمْ يَسْتَغْفِرُونَ}[ الذاريات: 18 ]  ، فجمعوا في ليلهم تلاوة كتاب الله - تعالى - ،  وسائر الأذكار المأثورة عن رسول الله - صلَّى الله عليه و سلَّم -  ، فللّه درُّه من ليل طاب بإحياء أهله له ، ويالخسارتنا وتهاوننا ، وتفريطنا ، بليالينا ، وأسحارنا ! وعسى أن تسلَم من عصيان إلهنا ، إلَّا ما رحم ربنا - تعالى -  .وعن حماد بن زيد : عن عطاء بن السائب ، أنَّ أبا عبد الرحمن قال :  أخذنا القرآن عن قوم أخبرونا أنهم كانوا إذا تعلموا عشر آيات ،لم يجاوزوهن إلى العشر الأخر حتى يعلموا ما فيهن ، فكنا نتعلم القرآن ، والعمل به ، وسيرث القرآن بعدنا قوم يشربونه شرب الماء لا يجاوز تراقيهم  انظر : سير أعلام النبلاء (4/ 269 ) . "},
        {"text": "الذِّكر فيه حياة للقلوب . \n\n كثير منَّا لاسيما في هذه الأزمان ، وكثرة الانشغال يشكو صدأ قلبه وغفلته ، وحياة القلب تكون بالذِّكر ، ففي صحيح البخاري من حديث أبي موسى - رضي الله عنه - قال: قال النبيُّ - صلَّى الله عليه وسلَّم - :  مَثَلُ الَّذِي يَذْكُرُ رَبَّهُ وَالَّذِي لَا يَذْكُرُ رَبَّهُ مَثَلُ الْحَيِّ وَالْمَيِّتِ ، وفي لفظ مسلم قال النَّبيُّ - صلَّى الله عليه وسلَّم - : مَثَلُ الْبَيْتِ الَّذِي يُذْكَرُ اللّهُ فِيهِ، وَالْبَيْتِ الَّذِي لاَ يُذْكَرُ اللّهُ فِيهِ، مَثَلُ الْحَيِّ وَالْمَيِّتِ  رواه البخاري برقم (6407)، رواه مسلم برقم (779) ."},
        {"text": "حث الله - عز وجلَّ - على ذِكْره في مواضع عديدة، منها: \n\n 1/ حث اللهُ - عز وجلّ- عباده على الإكثار من الذِّكر، فقال تعالى: {يَا أَيُّهَا الَّذِينَ آمَنُوا اذْكُرُوا اللَّهَ ذِكْرًا كَثِيرًا * وَسَبِّحُوهُ بُكْرَةً وَأَصِيلًا} \n\n [الأحزاب:41-42] \n\n2/ ووعد الله - تعالى - الذاكرين والذاكرات بالمغفرة والأجر العظيم، فقال تعالى: {وَالذَّاكِرِينَ اللَّهَ كَثِيرًا وَالذَّاكِرَاتِ أَعَدَّ اللَّهُ لَهُم مَّغْفِرَةً وَأَجْرًا عَظِيمًا} \n\n [الأحزاب:35] \n\n3/ وحذرنا الله - عز وجلَّ - من صفات المنافقين في قلة ذكرهم لله، فقال تعالى: {إِنَّ الْمُنَافِقِينَ يُخَادِعُونَ اللَّهَ وَهُوَ خَادِعُهُمْ وَإِذَا قَامُوا إِلَى الصَّلَاةِ قَامُوا كُسَالَى يُرَاءُونَ النَّاسَ وَلَا يَذْكُرُونَ اللَّهَ إِلَّا قَلِيلًا} \n\n [النساء:142] \n\n4/ وحذرنا الله - عز وجلَّ - من الانشغال عن ذكره بالأموال والأولاد، فقال تعالى: {يَا أَيُّهَا الَّذِينَ آمَنُوا لَا تُلْهِكُمْ أَمْوَالُكُمْ وَلَا أَوْلَادُكُمْ عَن ذِكْرِ اللَّهِ وَمَن يَفْعَلْ ذَلِكَ فَأُولَئِكَ هُمُ الْخَاسِرُونَ} \n\n [المنافقون:9] \n\n5/ وبيّن الله - عز وجلَّ - فضل الذكر العظيم في قوله: {فَاذْكُرُونِي أَذْكُرْكُمْ} \n\n [البقرة:152] \n\nوفي الحديث القدسي: أَنَا عِنْدَ ظَنِّ عَبْدِي بِي، وَأَنَا مَعَهُ إِذَا ذَكَرَنِي، فَإِنْ ذَكَرَنِي فِي نَفْسِهِ، ذَكَرْتُهُ فِي نَفْسِي، وَإِنْ ذَكَرَنِي فِي مَلَإٍ، ذَكَرْتُهُ فِي مَلَإٍ خَيْرٍ مِنْهُمْ \n\nرواه البخاري برقم 7405، ومسلم برقم 2675 عن أبي هريرة - رضي الله عنه - \n\nففي هذه الآيات والأحاديث فوائد عظيمة:- فضل كثرة ذكر الله تعالى- وجوب الحذر من قلة الذكر كالمنافقين- التحذير من الانشغال عن الذكر بالدنيا- عظم جزاء الذاكرين عند الله- شرف مصاحبة الله للذاكرين \n\nوينبغي للمسلم أن:- يواظب على الأذكار الشرعية- يجتهد في كثرة الذكر في جميع الأحوال- يحذر من الغفلة عن ذكر الله- يستشعر معية الله عند الذكر- يربّي أولاده على حب الذكر"},
        {"text": "من كنوز الذكر اليومية (1) \n\n 1. عن أبي هريرة - رضي الله عنه - أن رسول الله - صلَّى الله عليه وسلَّم - قال: مَنْ قَالَ: لَا إِلَهَ إِلَّا اللَّهُ وَحْدَهُ لَا شَرِيكَ لَهُ، لَهُ الْمُلْكُ وَلَهُ الْحَمْدُ، وَهُوَ عَلَى كُلِّ شَيْءٍ قَدِيرٌ، فِي يَوْمٍ مِائَةَ مَرَّةٍ، كَانَتْ لَهُ عِدْلَ عَشْرِ رِقَابٍ، وَكُتِبَتْ لَهُ مِائَةُ حَسَنَةٍ، وَمُحِيَتْ عَنْهُ مِائَةُ سَيِّئَةٍ، وَكَانَتْ لَهُ حِرْزًا مِنَ الشَّيْطَانِ يَوْمَهُ ذَلِكَ حَتَّى يُمْسِيَ، وَلَمْ يَأْتِ أَحَدٌ بِأَفْضَلَ مِمَّا جَاءَ بِهِ إِلَّا أَحَدٌ عَمِلَ أَكْثَرَ مِنْ ذَلِكَ. وَمَنْ قَالَ: سُبْحَانَ اللَّهِ وَبِحَمْدِهِ، فِي يَوْمٍ مِائَةَ مَرَّةٍ، حُطَّتْ خَطَايَاهُ، وَلَوْ كَانَتْ مِثْلَ زَبَدِ الْبَحْرِ \n\nرواه البخاري برقم 3293، ومسلم برقم 2691 \n\n2. وعن أبي أيوب - رضي الله عنه - قال النبي - صلَّى الله عليه وسلَّم -: مَنْ قَالَ: لَا إِلَهَ إِلَّا اللَّهُ وَحْدَهُ لَا شَرِيكَ لَهُ، لَهُ الْمُلْكُ وَلَهُ الْحَمْدُ وَهُوَ عَلَى كُلِّ شَيْءٍ قَدِيرٌ، عَشْرَ مِرَارٍ، كَانَ كَمَنْ أَعْتَقَ أَرْبَعَةَ أَنْفُسٍ مِنْ وَلَدِ إِسْمَاعِيلَ \n\nرواه البخاري برقم 6404، ومسلم برقم 2693 \n\n3. وعن أبي موسى الأشعري - رضي الله عنه - قال النبي - صلَّى الله عليه وسلَّم -: أَلَا أَدُلُّكُمْ عَلَى كَنْزٍ مِنْ كُنُوزِ الْجَنَّةِ؟ فَقَالَ: لَا حَوْلَ وَلَا قُوَّةَ إِلَّا بِاللَّهِ \n\nرواه البخاري برقم 6610، ومسلم برقم 2704 \n\n4. وعن أبي هريرة - رضي الله عنه - أن النبي - صلَّى الله عليه وسلَّم - قال: كَلِمَتَانِ خَفِيفَتَانِ عَلَى اللِّسَانِ، ثَقِيلَتَانِ فِي الْمِيزَانِ، حَبِيبَتَانِ إِلَى الرَّحْمَنِ: سُبْحَانَ اللَّهِ وَبِحَمْدِهِ، سُبْحَانَ اللَّهِ الْعَظِيمِ \n\nرواه البخاري برقم 7563، ومسلم برقم 2694 \n\n5. وعن أبي هريرة - رضي الله عنه - أن النبي - صلَّى الله عليه وسلَّم - قال: مَنْ قَالَ حِينَ يُصْبِحُ وَحِينَ يُمْسِي: سُبْحَانَ اللَّهِ وَبِحَمْدِهِ مِائَةَ مَرَّةٍ، لَمْ يَأْتِ أَحَدٌ يَوْمَ الْقِيَامَةِ بِأَفْضَلَ مِمَّا جَاءَ بِهِ، إِلَّا أَحَدٌ قَالَ مِثْلَ مَا قَالَ أَوْ زَادَ \n\nرواه مسلم برقم 2692 \n\nففي هذه الأحاديث فوائد عظيمة:- فضل الذكر عموماً والتسبيح والتهليل خصوصاً- عظم أجر الذاكرين عند الله تعالى- محو الخطايا والذنوب بالذكر- الحفظ من الشيطان وأذاه- مضاعفة الحسنات وتكفير السيئات \n\nوينبغي للمسلم أن:- يواظب على الأذكار الواردة- يحافظ على الأوقات المحددة للذكر- يستشعر معاني الأذكار- يحرص على تعليمها لأهله وأولاده- يجتهد في الإكثار من ذكر الله في جميع الأحوال"},
        {"text": "من كنوز الذكر اليومية (2) \n\n مما ورد في سُنَّة النَّبيّ - صلَّى الله عليه وسلَّم - من أنواع الذكر كثير، منها ما يلي:\n\n3. عن سعد بن أبي وقاص - رضي الله عنه - قال: كُنَّا عِنْدَ رَسُولِ اللّهِ - صَلَّى اللَّهُ عَلَيْهِ وَسَلَّمَ - فقال: أَيَعْجِزُ أَحَدُكُمْ أَنْ يَكْسِبَ، كُلَّ يَوْمٍ، أَلْفَ حَسَنَةٍ؟ فَسَأَلَهُ سَائِلٌ مِنْ جُلَسَائِهِ: كَيْفَ يَكْسِبُ أَحَدُنَا أَلْفَ حَسَنَةٍ؟ قَالَ: يُسَبِّحُ مِائَةَ تَسْبِيحَةٍ، فَيُكْتَبُ لَهُ أَلْفُ حَسَنَةٍ. أَوْ يُحَطُّ عَنْهُ أَلْفُ خَطِيئَةٍ رواه مسلم برقم (2698).\n\n4. عن أبي هريرة - رضي الله عنه - أنَّ رسول الله - صلَّى الله عليه وسلَّم - قال: مَنْ قَالَ سُبْحَانَ اللّهِ وَبِحَمْدِهِ فِي يَوْمٍ، مِائَةَ مَرَّةٍ، حُطَّتْ عنه خَطَايَاهُ وَإنْ كَانَتْ مِثْلَ زَبَدِ الْبَحْرِ رواه البخاري برقم (6405)، رواه مسلم برقم (2692).\n\nوفي رواية عند مسلم: مَنْ قَالَ حِينَ يُصْبِحُ وَحِينَ يُمْسِي: سُبْحَانَ اللّهِ وَبِحَمْدِهِ، مِائَةَ مَرَّةٍ، لَمْ يَأْتِ أَحَدٌ يَوْمَ الْقِيَامَةِ بِأَفْضَلَ مِمَّا جَاءَ بِهِ، إِلاَّ أَحَدٌ قَالَ مِثْلَ مَا قَالَ أَوْ زَادَ عَلَيْهِ رواه مسلم برقم (2692).\n\nوالأحاديث في أنواع الذِّكر وفضلها كثيرة، والذي تقدَّم هو من أشهر وأصحّ ما ورد من الذِّكر له فضل، وورد غيره كثير، فعن أبي موسى الأَشْعَرِي - رضي الله عنه – قال: قَالَ لِي رَسُولُ اللّهِ - صلَّى الله عليه وسلَّم -: أَلاَ أَدُلُّكَ عَلَى كَنْزٍ مِنْ كُنُوزِ الْجَنَّةِ؟ فَقُلْتُ: بَلَى. فَقَالَ: قُل لاَ حَوْلَ وَلاَ قُوَّةَ إِلاَّ بِاللّهِ رواه البخاري برقم (4202)، رواه مسلم برقم (2704).\n\nوعن أبي هريرة - رضي الله عنه - قال: قَالَ رَسُولُ اللّهِ - صلَّى الله عليه وسلَّم -: لأَنْ أَقُولَ: سُبْحَانَ اللّهِ، وَالْحَمْدُ للّهِ، وَلاَ إِلَـهَ إِلاَّ اللّهُ، وَاللّهُ أَكْبَرُ، أَحَبُّ إِلَيَّ مِمَّا طَلَعَتْ عَلَيْهِ الشَّمْسُ رواه مسلم برقم (2695)."},
        {"text": "من كنوز الذكر اليومية (3) \n\n والاستغفار أيضاً هو من أنواع الذِّكر، عن الأغرِّ المُزني - رضي الله عنه - قال النَّبيّ - صلَّى الله عليه وسلَّم -: إِنَّهُ لَيُغَانُ عَلَى قَلْبِي، وَإِنِّي لأَسْتَغْفِرُ اللّهَ فِي الْيَوْمِ مِائَةَ مَرَّةٍ رواه مسلم برقم (2702).\n\nوهذا فعله - صلَّى الله عليه وسلَّم -، وقد حثَّ على الاستغفار من قوله، كما في صحيح مسلم عن الأغرِّ - رضي الله عنه - أيضاً قال: قَالَ رَسُولُ اللّهِ - صلَّى الله عليه وسلَّم -: يا أيُّهَا النَّاسُ تُوبُوا إِلَى اللّهِ، فَإِنِّي أَتُوبُ فِي الْيَوْمِ إِلَيْهِ مِائَةَ مَرَّةٍ رواه مسلم برقم (2702).\n\nوعند البخاري من حديث أبي هريرة - رضي الله عنه - قال: سمعتُ رسولَ اللّهِ - صلَّى الله عليه وسلَّم - يقول: وَاللَّهِ إِنِّي لَأَسْتَغْفِرُ اللَّهَ وَأَتُوبُ إِلَيْهِ فِي الْيَوْمِ أَكْثَرَ مِنْ سَبْعِينَ مَرَّةً رواه البخاري برقم (6307)، فينبغي للعبد ألَّا يغفل عن الاستغفار.\n\nوأختم سُنَّة الذِّكر - وكذا جميع السُّنَن اليوميَّة - بذكر عظيم جاء في الصحيحين، وهو حديث أبي هريرة - رضي الله عنه – قال: قَالَ رَسُولُ اللّهِ - صلَّى الله عليه وسلَّم -: كَلِمَتَانِ خَفِيفَتَانِ عَلَى اللِّسَانِ، ثَقِيلَتَانِ فِي الْمِيزَانِ، حَبِيبَتَانِ إِلَى الرَّحْمنِ: سُبْحَانَ اللّه وَبِحَمْدِهِ، سُبْحَانَ اللّهِ الْعَظِيمِ رواه البخاري برقم (6406)، رواه مسلم برقم (2694)."}

    ]

}